{
  "type": "Feature",
  "properties": {
    "gn:admin1_code":"02",
    "gn:asciiname":"Aydere",
    "gn:country_code":"TM",
    "gn:dem":730,
    "gn:feature_class":"P",
    "gn:feature_code":"PPL",
    "gn:name":"Aydere",
    "gn:population":0,
    "gn:timezone":"Asia/Ashgabat",
    "iso:country":"TM",
    "name:rus_x_preferred":[
        "\u041d\u0438\u0436\u043d\u0438\u0439 \u0410\u0439\u0434\u0435\u0440\u0435"
    ],
    "name:und_x_variant":[
        "Nizhniy Aydere"
    ],
    "wof:name":"Aydere",
    "wof:placetype":"locality"
},
  "geometry": {"coordinates":[56.74856,38.40046],"type":"Point"}
}