{
  "type": "Feature",
  "properties": {
    "gn:admin1_code":"00",
    "gn:asciiname":"Koshagyr",
    "gn:country_code":"TM",
    "gn:dem":333,
    "gn:feature_class":"P",
    "gn:feature_code":"PPL",
    "gn:name":"Koshagyr",
    "gn:population":0,
    "gn:timezone":"Asia/Ashgabat",
    "iso:country":"TM",
    "wof:name":"Koshagyr",
    "wof:placetype":"locality"
},
  "geometry": {"coordinates":[54.60021,39.79658],"type":"Point"}
}