{
  "type": "Feature",
  "properties": {
    "gn:admin1_code":"00",
    "gn:asciiname":"Bol'shevik",
    "gn:country_code":"TM",
    "gn:dem":184,
    "gn:feature_class":"P",
    "gn:feature_code":"PPL",
    "gn:name":"Bol\u2019shevik",
    "gn:population":0,
    "gn:timezone":"Asia/Ashgabat",
    "iso:country":"TM",
    "wof:name":"Bol'shevik",
    "wof:placetype":"locality"
},
  "geometry": {"coordinates":[63.34793000000001,39.22073],"type":"Point"}
}