{
  "type": "Feature",
  "properties": {
    "gn:admin1_code":"00",
    "gn:asciiname":"Imeni Karla Marksa",
    "gn:country_code":"TM",
    "gn:dem":222,
    "gn:feature_class":"P",
    "gn:feature_code":"PPL",
    "gn:name":"Imeni Karla Marksa",
    "gn:population":0,
    "gn:timezone":"Asia/Ashgabat",
    "iso:country":"TM",
    "wof:name":"Imeni Karla Marksa",
    "wof:placetype":"locality"
},
  "geometry": {"coordinates":[61.91667,37.58333],"type":"Point"}
}