{
  "type": "Feature",
  "properties": {
    "gn:admin1_code":"01",
    "gn:asciiname":"Shamli",
    "gn:country_code":"TM",
    "gn:dem":623,
    "gn:feature_class":"P",
    "gn:feature_code":"PPL",
    "gn:name":"Shamli",
    "gn:population":0,
    "gn:timezone":"Asia/Ashgabat",
    "iso:country":"TM",
    "name:rus_x_preferred":[
        "\u0428\u0430\u043c\u043b\u0438"
    ],
    "name:und_x_variant":[
        "Shemli"
    ],
    "wof:name":"Shamli",
    "wof:placetype":"locality"
},
  "geometry": {"coordinates":[58.68065,37.70727],"type":"Point"}
}