{
  "type": "Feature",
  "properties": {
    "gn:admin1_code":"01",
    "gn:asciiname":"Dowletabat",
    "gn:country_code":"TM",
    "gn:dem":287,
    "gn:feature_class":"P",
    "gn:feature_code":"PPL",
    "gn:name":"D\u00f6wletabat",
    "gn:population":0,
    "gn:timezone":"Asia/Ashgabat",
    "iso:country":"TM",
    "name:tuk_x_preferred":[
        "D\u00f6wletabat"
    ],
    "name:und_x_variant":[
        "Sovetabad"
    ],
    "wof:name":"Dowletabat",
    "wof:placetype":"locality"
},
  "geometry": {"coordinates":[61.43337,36.47442],"type":"Point"}
}