{
  "type": "Feature",
  "properties": {
    "gn:admin1_code":"00",
    "gn:asciiname":"Kabasakal",
    "gn:country_code":"TM",
    "gn:dem":241,
    "gn:feature_class":"P",
    "gn:feature_code":"PPL",
    "gn:name":"Kabasakal",
    "gn:population":0,
    "gn:timezone":"Asia/Ashgabat",
    "iso:country":"TM",
    "name:ceb_x_preferred":[
        "Kabasakal"
    ],
    "name:msa_x_preferred":[
        "Kabasakal"
    ],
    "name:tur_x_preferred":[
        "Kabasakal"
    ],
    "name:vie_x_preferred":[
        "Kabasakal"
    ],
    "wof:name":"Kabasakal",
    "wof:placetype":"locality"
},
  "geometry": {"coordinates":[65.15000000000001,37.86667],"type":"Point"}
}