{
  "type": "Feature",
  "properties": {
    "gn:admin1_code":"00",
    "gn:asciiname":"Vekil'-Bazar",
    "gn:country_code":"TM",
    "gn:dem":224,
    "gn:feature_class":"P",
    "gn:feature_code":"PPL",
    "gn:name":"Vekil\u2019-Bazar",
    "gn:population":0,
    "gn:timezone":"Asia/Ashgabat",
    "iso:country":"TM",
    "wof:name":"Vekil'-Bazar",
    "wof:placetype":"locality"
},
  "geometry": {"coordinates":[61.93944000000001,37.63638],"type":"Point"}
}