{
  "type": "Feature",
  "properties": {
    "gn:country":"TM",
    "gn:fcode":"PPL",
    "gn:population":21159,
    "iso:country":"TM",
    "name:bul_x_preferred":[
        "\u0411\u043e\u043b\u0434\u0443\u043c\u0441\u0430\u0437"
    ],
    "name:ceb_x_preferred":[
        "Boldumsaz"
    ],
    "name:ell_x_preferred":[
        "\u039c\u03c0\u03bf\u03bb\u03bd\u03c4\u03bf\u03c5\u03bc\u03c3\u03ac\u03b6"
    ],
    "name:eng_x_preferred":[
        "Boldumsaz"
    ],
    "name:est_x_preferred":[
        "Boldumsaz"
    ],
    "name:hsb_x_preferred":[
        "Boldumsaz"
    ],
    "name:ita_x_preferred":[
        "Boldumsaz"
    ],
    "name:nld_x_preferred":[
        "Boldumsaz"
    ],
    "name:pnb_x_preferred":[
        "\u0628\u0648\u0644\u062f\u0648\u0645 \u0633\u0627\u0632"
    ],
    "name:pol_x_preferred":[
        "Boldumsaz"
    ],
    "name:rus_x_preferred":[
        "\u0411\u043e\u043b\u0434\u0443\u043c\u0441\u0430\u0437"
    ],
    "name:spa_x_preferred":[
        "Boldumsaz"
    ],
    "name:tat_x_preferred":[
        "\u0411\u0443\u043b\u0434\u044b\u043c\u0441\u0430\u0437"
    ],
    "name:und_x_variant":[
        "Kalinin"
    ],
    "name:urd_x_preferred":[
        "\u0628\u0648\u0644\u062f\u0648\u0645\u0633\u0627\u0632"
    ],
    "qs:name":"Boldumsaz",
    "qs:photos_9r":0,
    "qs:photos_sr":0,
    "qs:pop_sr":"7",
    "wd:wordcount":15,
    "wof:name":"Boldumsaz",
    "wof:placetype":"locality",
    "wof:population":21159
},
  "geometry": {"coordinates":[59.67101,42.12824],"type":"Point"}
}