{
  "type": "Feature",
  "properties": {
    "gn:admin1_code":"00",
    "gn:asciiname":"Mamed'yar",
    "gn:country_code":"TM",
    "gn:dem":87,
    "gn:feature_class":"P",
    "gn:feature_code":"PPL",
    "gn:name":"Mamed\u2019yar",
    "gn:population":0,
    "gn:timezone":"Asia/Ashgabat",
    "iso:country":"TM",
    "wof:name":"Mamed'yar",
    "wof:placetype":"locality"
},
  "geometry": {"coordinates":[58.45,38.86667],"type":"Point"}
}