{
  "type": "Feature",
  "properties": {
    "gn:admin1_code":"02",
    "gn:asciiname":"Bugdayly",
    "gn:country_code":"TM",
    "gn:dem":0,
    "gn:feature_class":"P",
    "gn:feature_code":"PPL",
    "gn:name":"Bugdayly",
    "gn:population":0,
    "gn:timezone":"Asia/Ashgabat",
    "iso:country":"TM",
    "name:und_x_variant":[
        "Bugdayli",
        "Bugdayly"
    ],
    "wof:name":"Bugdayly",
    "wof:placetype":"locality"
},
  "geometry": {"coordinates":[54.37478,38.49467],"type":"Point"}
}