{
  "type": "Feature",
  "properties": {
    "gn:admin1_code":"00",
    "gn:asciiname":"Imeni Gorel'de",
    "gn:country_code":"TM",
    "gn:dem":209,
    "gn:feature_class":"P",
    "gn:feature_code":"PPL",
    "gn:name":"Imeni Gorel\u2019de",
    "gn:population":0,
    "gn:timezone":"Asia/Ashgabat",
    "iso:country":"TM",
    "name:und_x_variant":[
        "Kochev\u2019y\u00eb Uchinchi-Kara-Yab",
        "Moskva",
        "Imeni Gorel\u2019de"
    ],
    "wof:name":"Imeni Gorel'de",
    "wof:placetype":"locality"
},
  "geometry": {"coordinates":[61.63267,37.73975],"type":"Point"}
}