{
  "type": "Feature",
  "properties": {
    "gn:admin1_code":"01",
    "gn:asciiname":"Gurgulab",
    "gn:country_code":"TM",
    "gn:dem":893,
    "gn:feature_class":"P",
    "gn:feature_code":"PPL",
    "gn:name":"Gurgulab",
    "gn:population":0,
    "gn:timezone":"Asia/Ashgabat",
    "iso:country":"TM",
    "name:rus_x_preferred":[
        "\u041a\u0443\u0440\u043a\u0443\u043b\u0430\u0431"
    ],
    "name:tuk_x_preferred":[
        "Gurgulab"
    ],
    "name:und_x_variant":[
        "Dmitriyevskiy",
        "Kurkulab"
    ],
    "wof:name":"Gurgulab",
    "wof:placetype":"locality"
},
  "geometry": {"coordinates":[57.66731,38.03113],"type":"Point"}
}