{
  "type": "Feature",
  "properties": {
    "gn:admin1_code":"00",
    "gn:asciiname":"Zakhmet",
    "gn:country_code":"TM",
    "gn:dem":155,
    "gn:feature_class":"P",
    "gn:feature_code":"PPL",
    "gn:name":"Zakhmet",
    "gn:population":0,
    "gn:timezone":"Asia/Ashgabat",
    "iso:country":"TM",
    "wof:name":"Zakhmet",
    "wof:placetype":"locality"
},
  "geometry": {"coordinates":[60.26667,37.85],"type":"Point"}
}