{
  "type": "Feature",
  "properties": {
    "gn:admin1_code":"00",
    "gn:asciiname":"Arychagyl",
    "gn:country_code":"TM",
    "gn:dem":64,
    "gn:feature_class":"P",
    "gn:feature_code":"PPL",
    "gn:name":"Arychagyl",
    "gn:population":0,
    "gn:timezone":"Asia/Ashgabat",
    "iso:country":"TM",
    "wof:name":"Arychagyl",
    "wof:placetype":"locality"
},
  "geometry": {"coordinates":[58.71666999999999,42.55],"type":"Point"}
}