{
  "type": "Feature",
  "properties": {
    "gn:admin1_code":"00",
    "gn:asciiname":"Alnysh",
    "gn:country_code":"TM",
    "gn:dem":260,
    "gn:feature_class":"P",
    "gn:feature_code":"PPL",
    "gn:name":"Alnysh",
    "gn:population":0,
    "gn:timezone":"Asia/Ashgabat",
    "iso:country":"TM",
    "name:und_x_variant":[
        "Almysh",
        "Alnysh"
    ],
    "wof:name":"Alnysh",
    "wof:placetype":"locality"
},
  "geometry": {"coordinates":[62.38501,37.26089],"type":"Point"}
}