{
  "type": "Feature",
  "properties": {
    "gn:admin1_code":"00",
    "gn:asciiname":"Tezeyol",
    "gn:country_code":"TM",
    "gn:dem":156,
    "gn:feature_class":"P",
    "gn:feature_code":"PPL",
    "gn:name":"Tezeyol",
    "gn:population":0,
    "gn:timezone":"Asia/Ashgabat",
    "iso:country":"TM",
    "wof:name":"Tezeyol",
    "wof:placetype":"locality"
},
  "geometry": {"coordinates":[60.3273,37.90126],"type":"Point"}
}