{
  "type": "Feature",
  "properties": {
    "gn:admin1_code":"05",
    "gn:asciiname":"Cemenebit",
    "gn:cc2":"TM",
    "gn:country_code":"TM",
    "gn:dem":523,
    "gn:feature_class":"P",
    "gn:feature_code":"PPL",
    "gn:name":"\u00c7emenebit",
    "gn:population":0,
    "gn:timezone":"Asia/Ashgabat",
    "iso:country":"TM",
    "name:tuk_x_preferred":[
        "\u00c7emenebit"
    ],
    "name:tuk_x_variant":[
        "\u00c7emenibit"
    ],
    "name:und_x_variant":[
        "Chemen-i-Bid",
        "Chemenibit"
    ],
    "wof:name":"Cemenebit",
    "wof:placetype":"locality"
},
  "geometry": {"coordinates":[62.39583,35.44889000000001],"type":"Point"}
}