{
  "type": "Feature",
  "properties": {
    "gn:admin1_code":"S",
    "gn:asciiname":"Gyami",
    "gn:country_code":"TM",
    "gn:dem":244,
    "gn:feature_class":"P",
    "gn:feature_code":"PPL",
    "gn:name":"Gyami",
    "gn:population":0,
    "gn:timezone":"Asia/Ashgabat",
    "iso:country":"TM",
    "name:rus_x_preferred":[
        "\u0413\u0435\u0430\u043c\u0438"
    ],
    "name:tuk_x_preferred":[
        "G\u00e4mi"
    ],
    "name:und_x_variant":[
        "Geami",
        "Gyami"
    ],
    "wof:name":"Gyami",
    "wof:placetype":"locality"
},
  "geometry": {"coordinates":[58.47039,37.90735],"type":"Point"}
}