{
  "type": "Feature",
  "properties": {
    "gn:admin1_code":"01",
    "gn:asciiname":"Akhtash-Ovliya",
    "gn:country_code":"TM",
    "gn:dem":399,
    "gn:feature_class":"P",
    "gn:feature_code":"PPL",
    "gn:name":"Akhtash-Ovliya",
    "gn:population":0,
    "gn:timezone":"Asia/Ashgabat",
    "iso:country":"TM",
    "wof:name":"Akhtash-Ovliya",
    "wof:placetype":"locality"
},
  "geometry": {"coordinates":[61.21666999999999,36.28333],"type":"Point"}
}