{
  "type": "Feature",
  "properties": {
    "gn:admin1_code":"05",
    "gn:asciiname":"Kushka",
    "gn:country_code":"TM",
    "gn:dem":730,
    "gn:feature_class":"P",
    "gn:feature_code":"PPL",
    "gn:name":"Kushka",
    "gn:population":0,
    "gn:timezone":"Asia/Ashgabat",
    "iso:country":"TM",
    "name:und_x_variant":[
        "Krepost\u2019 Kushka",
        "Kushka"
    ],
    "wof:name":"Kushka",
    "wof:placetype":"locality"
},
  "geometry": {"coordinates":[62.33333,35.26667],"type":"Point"}
}