{
  "type": "Feature",
  "properties": {
    "gn:admin1_code":"00",
    "gn:asciiname":"Archin",
    "gn:country_code":"TM",
    "gn:dem":176,
    "gn:feature_class":"P",
    "gn:feature_code":"PPL",
    "gn:name":"Archin",
    "gn:population":0,
    "gn:timezone":"Asia/Ashgabat",
    "iso:country":"TM",
    "wof:name":"Archin",
    "wof:placetype":"locality"
},
  "geometry": {"coordinates":[60.33333,37.46667],"type":"Point"}
}