{
  "type": "Feature",
  "properties": {
    "gn:admin1_code":"04",
    "gn:asciiname":"Imeni Il'icha",
    "gn:country_code":"TM",
    "gn:dem":199,
    "gn:feature_class":"P",
    "gn:feature_code":"PPL",
    "gn:name":"Imeni Il\u2019icha",
    "gn:population":0,
    "gn:timezone":"Asia/Ashgabat",
    "iso:country":"TM",
    "name:und_x_variant":[
        "Kyzan",
        "Imeni Lenina",
        "Kyzak",
        "Imeni Il\u2019icha"
    ],
    "wof:name":"Imeni Il'icha",
    "wof:placetype":"locality"
},
  "geometry": {"coordinates":[63.80833000000001,38.86222],"type":"Point"}
}