{
  "type": "Feature",
  "properties": {
    "gn:admin1_code":"01",
    "gn:asciiname":"Khadzhibulan",
    "gn:country_code":"TM",
    "gn:dem":376,
    "gn:feature_class":"P",
    "gn:feature_code":"PPL",
    "gn:name":"Khadzhibulan",
    "gn:population":0,
    "gn:timezone":"Asia/Ashgabat",
    "iso:country":"TM",
    "name:und_x_variant":[
        "Khodzha-Bulak",
        "Khodzha-Bulan",
        "Khadzhibulan"
    ],
    "wof:name":"Khadzhibulan",
    "wof:placetype":"locality"
},
  "geometry": {"coordinates":[60.11075,37.01232],"type":"Point"}
}