{
  "type": "Feature",
  "properties": {
    "gn:admin1_code":"04",
    "gn:asciiname":"Imeni Kirova",
    "gn:cc2":"TM",
    "gn:country_code":"TM",
    "gn:dem":160,
    "gn:feature_class":"P",
    "gn:feature_code":"PPL",
    "gn:name":"Imeni Kirova",
    "gn:population":0,
    "gn:timezone":"Asia/Ashgabat",
    "iso:country":"TM",
    "name:ceb_x_preferred":[
        "Imeni Kirova"
    ],
    "name:swe_x_preferred":[
        "Imeni Kirova"
    ],
    "name:und_x_variant":[
        "Kabakly-Kurgan",
        "Kavakhly-Kurgan",
        "Kavakly-Kurgan"
    ],
    "wof:name":"Imeni Kirova",
    "wof:placetype":"locality"
},
  "geometry": {"coordinates":[62.52306,39.815],"type":"Point"}
}