{
  "type": "Feature",
  "properties": {
    "gn:admin1_code":"04",
    "gn:asciiname":"Kazarma",
    "gn:country_code":"TM",
    "gn:dem":315,
    "gn:feature_class":"P",
    "gn:feature_code":"PPL",
    "gn:name":"Kazarma",
    "gn:population":0,
    "gn:timezone":"Asia/Ashgabat",
    "iso:country":"TM",
    "name:msa_x_preferred":[
        "Kazarma"
    ],
    "wof:name":"Kazarma",
    "wof:placetype":"locality"
},
  "geometry": {"coordinates":[65.93486999999999,37.79059],"type":"Point"}
}