{
  "type": "Feature",
  "properties": {
    "gn:admin1_code":"02",
    "gn:asciiname":"Garajabatyr",
    "gn:cc2":"TM",
    "gn:country_code":"TM",
    "gn:dem":-3,
    "gn:feature_class":"P",
    "gn:feature_code":"PPL",
    "gn:name":"Garajabatyr",
    "gn:population":0,
    "gn:timezone":"Asia/Ashgabat",
    "iso:country":"TM",
    "name:rus_x_preferred":[
        "\u041a\u0430\u0440\u0430\u0434\u0436\u0430-\u0411\u0430\u0442\u044b\u0440"
    ],
    "name:und_x_variant":[
        "Karadzha-Batyr",
        "Garajabatyr"
    ],
    "wof:name":"Garajabatyr",
    "wof:placetype":"locality"
},
  "geometry": {"coordinates":[54.42278,37.64639],"type":"Point"}
}