{
  "type": "Feature",
  "properties": {
    "gn:admin1_code":"01",
    "gn:asciiname":"Koyno-Kumbez",
    "gn:country_code":"TM",
    "gn:dem":1350,
    "gn:feature_class":"P",
    "gn:feature_code":"PPL",
    "gn:name":"Koyno-Kumbez",
    "gn:population":0,
    "gn:timezone":"Asia/Ashgabat",
    "iso:country":"TM",
    "name:rus_x_preferred":[
        "\u041a\u0451\u043d\u0435-\u041a\u0443\u043c\u0431\u0435\u0437"
    ],
    "name:und_x_variant":[
        "K\u00ebne-Kumbez"
    ],
    "wof:name":"Koyno-Kumbez",
    "wof:placetype":"locality"
},
  "geometry": {"coordinates":[56.95922,38.3868],"type":"Point"}
}