{
  "type": "Feature",
  "properties": {
    "gn:admin1_code":"00",
    "gn:asciiname":"Kyrkuyli",
    "gn:cc2":"TM",
    "gn:country_code":"TM",
    "gn:dem":229,
    "gn:feature_class":"P",
    "gn:feature_code":"PPL",
    "gn:name":"Kyrkuyli",
    "gn:population":0,
    "gn:timezone":"Asia/Ashgabat",
    "iso:country":"TM",
    "name:und_x_variant":[
        "Kyrk-Uyle",
        "Kyrkuyli"
    ],
    "wof:name":"Kyrkuyli",
    "wof:placetype":"locality"
},
  "geometry": {"coordinates":[65.09999999999999,38.06667],"type":"Point"}
}