{
  "type": "Feature",
  "properties": {
    "gn:admin1_code":"02",
    "gn:asciiname":"Dardali",
    "gn:country_code":"TM",
    "gn:dem":320,
    "gn:feature_class":"P",
    "gn:feature_code":"PPL",
    "gn:name":"Dardali",
    "gn:population":0,
    "gn:timezone":"Asia/Ashgabat",
    "iso:country":"TM",
    "wof:name":"Dardali",
    "wof:placetype":"locality"
},
  "geometry": {"coordinates":[56.03333000000001,38.15],"type":"Point"}
}