{
  "type": "Feature",
  "properties": {
    "gn:admin1_code":"00",
    "gn:asciiname":"Chash-Kala",
    "gn:country_code":"TM",
    "gn:dem":141,
    "gn:feature_class":"P",
    "gn:feature_code":"PPL",
    "gn:name":"Chash-Kala",
    "gn:population":0,
    "gn:timezone":"Asia/Ashgabat",
    "iso:country":"TM",
    "name:und_x_variant":[
        "Kala",
        "Chash-Kala"
    ],
    "wof:name":"Chash-Kala",
    "wof:placetype":"locality"
},
  "geometry": {"coordinates":[62.02905,40.96685],"type":"Point"}
}