{
  "type": "Feature",
  "properties": {
    "gn:admin1_code":"04",
    "gn:asciiname":"Akkumulam",
    "gn:country_code":"TM",
    "gn:dem":259,
    "gn:feature_class":"P",
    "gn:feature_code":"PPL",
    "gn:name":"Akkumulam",
    "gn:population":0,
    "gn:timezone":"Asia/Ashgabat",
    "iso:country":"TM",
    "name:und_x_variant":[
        "Ulyam",
        "Akkumulyam",
        "Akkumulam"
    ],
    "wof:name":"Akkumulam",
    "wof:placetype":"locality"
},
  "geometry": {"coordinates":[65.87045999999999,37.53717],"type":"Point"}
}