{
  "type": "Feature",
  "properties": {
    "gn:admin1_code":"05",
    "gn:asciiname":"Imeni Stalina",
    "gn:cc2":"TM",
    "gn:country_code":"TM",
    "gn:dem":345,
    "gn:feature_class":"P",
    "gn:feature_code":"PPL",
    "gn:name":"Imeni Stalina",
    "gn:population":0,
    "gn:timezone":"Asia/Ashgabat",
    "iso:country":"TM",
    "name:und_x_variant":[
        "Kizyl",
        "Imeni Stalina"
    ],
    "wof:name":"Imeni Stalina",
    "wof:placetype":"locality"
},
  "geometry": {"coordinates":[62.92417,35.94860999999999],"type":"Point"}
}