{
  "type": "Feature",
  "properties": {
    "gn:admin1_code":"00",
    "gn:asciiname":"Krestovskiy",
    "gn:country_code":"TM",
    "gn:dem":243,
    "gn:feature_class":"P",
    "gn:feature_code":"PPL",
    "gn:name":"Krestovskiy",
    "gn:population":0,
    "gn:timezone":"Asia/Ashgabat",
    "iso:country":"TM",
    "wof:name":"Krestovskiy",
    "wof:placetype":"locality"
},
  "geometry": {"coordinates":[62.23333,37.46667],"type":"Point"}
}