{
  "type": "Feature",
  "properties": {
    "gn:admin1_code":"00",
    "gn:asciiname":"Kizyl-Ishchi",
    "gn:cc2":"TM",
    "gn:country_code":"TM",
    "gn:dem":172,
    "gn:feature_class":"P",
    "gn:feature_code":"PPL",
    "gn:name":"Kizyl-Ishchi",
    "gn:population":0,
    "gn:timezone":"Asia/Ashgabat",
    "iso:country":"TM",
    "name:und_x_variant":[
        "Kyzyl-Ishchi",
        "Kizyl-Ishchi"
    ],
    "wof:name":"Kizyl-Ishchi",
    "wof:placetype":"locality"
},
  "geometry": {"coordinates":[60.28333000000001,37.53333],"type":"Point"}
}