{
  "type": "Feature",
  "properties": {
    "gn:admin1_code":"00",
    "gn:asciiname":"Oktyabr'",
    "gn:country_code":"TM",
    "gn:dem":78,
    "gn:feature_class":"P",
    "gn:feature_code":"PPL",
    "gn:name":"Oktyabr\u2019",
    "gn:population":0,
    "gn:timezone":"Asia/Ashgabat",
    "iso:country":"TM",
    "wof:name":"Oktyabr'",
    "wof:placetype":"locality"
},
  "geometry": {"coordinates":[59.71666999999999,42.23333],"type":"Point"}
}