{
  "type": "Feature",
  "properties": {
    "gn:admin1_code":"00",
    "gn:asciiname":"Segli-Kar",
    "gn:cc2":"TM",
    "gn:country_code":"TM",
    "gn:dem":219,
    "gn:feature_class":"P",
    "gn:feature_code":"PPL",
    "gn:name":"Segli-Kar",
    "gn:population":0,
    "gn:timezone":"Asia/Ashgabat",
    "iso:country":"TM",
    "name:und_x_variant":[
        "Segli-Khar-Kurama",
        "Segli-Kar"
    ],
    "wof:name":"Segli-Kar",
    "wof:placetype":"locality"
},
  "geometry": {"coordinates":[61.86666999999999,37.66667],"type":"Point"}
}