{
  "type": "Feature",
  "properties": {
    "gn:admin1_code":"05",
    "gn:asciiname":"Akrabat",
    "gn:country_code":"TM",
    "gn:dem":715,
    "gn:feature_class":"P",
    "gn:feature_code":"PPL",
    "gn:name":"Akrabat",
    "gn:population":0,
    "gn:timezone":"Asia/Ashgabat",
    "iso:country":"TM",
    "wof:name":"Akrabat",
    "wof:placetype":"locality"
},
  "geometry": {"coordinates":[61.71032,35.47824],"type":"Point"}
}