{
  "type": "Feature",
  "properties": {
    "gn:admin1_code":"01",
    "gn:asciiname":"Bol'shevik",
    "gn:country_code":"TM",
    "gn:dem":153,
    "gn:feature_class":"P",
    "gn:feature_code":"PPL",
    "gn:name":"Bol\u2019shevik",
    "gn:population":0,
    "gn:timezone":"Asia/Ashgabat",
    "iso:country":"TM",
    "name:rus_x_preferred":[
        "Bol\u2019shevik"
    ],
    "name:rus_x_variant":[
        "\u0411\u043e\u043b\u044c\u0448\u0435\u0432\u0438\u043a"
    ],
    "wof:name":"Bol'shevik",
    "wof:placetype":"locality"
},
  "geometry": {"coordinates":[57.96935,38.23456],"type":"Point"}
}