{
  "type": "Feature",
  "properties": {
    "gn:admin1_code":"01",
    "gn:asciiname":"Salmiin",
    "gn:country_code":"TM",
    "gn:dem":1021,
    "gn:feature_class":"P",
    "gn:feature_code":"PPL",
    "gn:name":"Salmiin",
    "gn:population":0,
    "gn:timezone":"Asia/Ashgabat",
    "iso:country":"TM",
    "name:rus_x_preferred":[
        "\u041b\u0435\u0442\u043d\u0438\u043a \u0421\u0430\u043b\u043c\u0438\u043d"
    ],
    "name:und_x_variant":[
        "Letnik Salmin"
    ],
    "wof:name":"Salmiin",
    "wof:placetype":"locality"
},
  "geometry": {"coordinates":[56.74231,38.57366],"type":"Point"}
}