{
  "type": "Feature",
  "properties": {
    "gn:admin1_code":"00",
    "gn:asciiname":"Erdel'",
    "gn:country_code":"TM",
    "gn:dem":185,
    "gn:feature_class":"P",
    "gn:feature_code":"PPL",
    "gn:name":"Erdel\u2019",
    "gn:population":0,
    "gn:timezone":"Asia/Ashgabat",
    "iso:country":"TM",
    "wof:name":"Erdel'",
    "wof:placetype":"locality"
},
  "geometry": {"coordinates":[63.35,39.23333],"type":"Point"}
}