{
  "type": "Feature",
  "properties": {
    "gn:admin1_code":"01",
    "gn:asciiname":"Sekizyap",
    "gn:country_code":"TM",
    "gn:dem":310,
    "gn:feature_class":"P",
    "gn:feature_code":"PPL",
    "gn:name":"Sekiz\u00fdap",
    "gn:population":0,
    "gn:timezone":"Asia/Ashgabat",
    "iso:country":"TM",
    "name:rus_x_preferred":[
        "Psikhicheskaya Bol\u2019nitsa Dva"
    ],
    "name:rus_x_variant":[
        "\u041f\u0441\u0438\u0445\u0438\u0447\u0435\u0441\u043a\u0430\u044f \u0411\u043e\u043b\u044c\u043d\u0438\u0446\u0430 \u0414\u0432\u0430"
    ],
    "name:tuk_x_preferred":[
        "Sekiz\u00fdap"
    ],
    "wof:name":"Sekizyap",
    "wof:placetype":"locality"
},
  "geometry": {"coordinates":[57.91597,38.09755],"type":"Point"}
}