{
  "type": "Feature",
  "properties": {
    "gn:admin1_code":"01",
    "gn:asciiname":"Epo",
    "gn:country_code":"TM",
    "gn:dem":261,
    "gn:feature_class":"P",
    "gn:feature_code":"PPL",
    "gn:name":"Epo",
    "gn:population":0,
    "gn:timezone":"Asia/Ashgabat",
    "iso:country":"TM",
    "wof:name":"Epo",
    "wof:placetype":"locality"
},
  "geometry": {"coordinates":[61.15,36.68333],"type":"Point"}
}