{
  "type": "Feature",
  "properties": {
    "gn:admin1_code":"00",
    "gn:asciiname":"Kommunizm",
    "gn:country_code":"TM",
    "gn:dem":223,
    "gn:feature_class":"P",
    "gn:feature_code":"PPL",
    "gn:name":"Kommunizm",
    "gn:population":0,
    "gn:timezone":"Asia/Ashgabat",
    "iso:country":"TM",
    "name:fas_x_preferred":[
        "\u06a9\u0645\u0648\u0646\u06cc\u0632\u0645"
    ],
    "name:msa_x_preferred":[
        "Kommunizm"
    ],
    "name:tgk_x_preferred":[
        "\u0414\u0435\u04b3\u043e\u0442\u0438 \u0417\u0430\u0440\u04b3\u0430\u043b\u043e\u043b"
    ],
    "name:und_x_variant":[
        "Amansha",
        "Anansha",
        "Kommunizm"
    ],
    "name:urd_x_preferred":[
        "\u06a9\u0645\u0648\u0646\u06cc\u0632\u0645"
    ],
    "wof:name":"Kommunizm",
    "wof:placetype":"locality"
},
  "geometry": {"coordinates":[61.92482,37.61185],"type":"Point"}
}