{
  "type": "Feature",
  "properties": {
    "gn:admin1_code":"00",
    "gn:asciiname":"Kommunizm",
    "gn:country_code":"TM",
    "gn:dem":223,
    "gn:feature_class":"P",
    "gn:feature_code":"PPL",
    "gn:name":"Kommunizm",
    "gn:population":0,
    "gn:timezone":"Asia/Ashgabat",
    "iso:country":"TM",
    "name:und_x_variant":[
        "Amansha",
        "Anansha",
        "Kommunizm"
    ],
    "wof:name":"Kommunizm",
    "wof:placetype":"locality"
},
  "geometry": {"coordinates":[61.92482,37.61185],"type":"Point"}
}