{
  "type": "Feature",
  "properties": {
    "gn:admin1_code":"00",
    "gn:asciiname":"Imeni Stalina",
    "gn:country_code":"TM",
    "gn:dem":263,
    "gn:feature_class":"P",
    "gn:feature_code":"PPL",
    "gn:name":"Imeni Stalina",
    "gn:population":0,
    "gn:timezone":"Asia/Ashgabat",
    "iso:country":"TM",
    "wof:name":"Imeni Stalina",
    "wof:placetype":"locality"
},
  "geometry": {"coordinates":[62.25,37.18333],"type":"Point"}
}