{
  "type": "Feature",
  "properties": {
    "gn:admin1_code":"04",
    "gn:asciiname":"Khadzhikaraul",
    "gn:country_code":"TM",
    "gn:dem":536,
    "gn:feature_class":"P",
    "gn:feature_code":"PPL",
    "gn:name":"Khadzhikaraul",
    "gn:population":0,
    "gn:timezone":"Asia/Ashgabat",
    "iso:country":"TM",
    "name:und_x_variant":[
        "Khodzha-Karaul",
        "Khadzhikaraul"
    ],
    "wof:name":"Khadzhikaraul",
    "wof:placetype":"locality"
},
  "geometry": {"coordinates":[66.37149000000001,37.74669],"type":"Point"}
}