{
  "type": "Feature",
  "properties": {
    "gn:admin1_code":"04",
    "gn:asciiname":"Etbashi",
    "gn:country_code":"TM",
    "gn:dem":223,
    "gn:feature_class":"P",
    "gn:feature_code":"PPL",
    "gn:name":"Etbashi",
    "gn:population":0,
    "gn:timezone":"Asia/Ashgabat",
    "iso:country":"TM",
    "name:und_x_variant":[
        "Etbash",
        "Etbashi"
    ],
    "wof:name":"Etbashi",
    "wof:placetype":"locality"
},
  "geometry": {"coordinates":[64.47041,38.23451],"type":"Point"}
}