{
  "type": "Feature",
  "properties": {
    "gn:admin1_code":"02",
    "gn:asciiname":"Gyzylsuw",
    "gn:country_code":"TM",
    "gn:dem":-22,
    "gn:feature_class":"P",
    "gn:feature_code":"PPL",
    "gn:name":"Gyzylsuw",
    "gn:population":0,
    "gn:timezone":"Asia/Ashgabat",
    "iso:country":"TM",
    "name:und_x_variant":[
        "Mys It-Balyk",
        "Gyzyl-Suv",
        "Kizil-Su",
        "Kyzylsu",
        "Kizyl-Su",
        "Gyzylsuw"
    ],
    "wof:name":"Gyzylsuw",
    "wof:placetype":"locality"
},
  "geometry": {"coordinates":[53.01361,39.79901],"type":"Point"}
}