{
  "type": "Feature",
  "properties": {
    "gn:admin1_code":"S",
    "gn:asciiname":"Berzengi",
    "gn:country_code":"TM",
    "gn:dem":325,
    "gn:feature_class":"P",
    "gn:feature_code":"PPL",
    "gn:name":"Berzengi",
    "gn:population":0,
    "gn:timezone":"Asia/Ashgabat",
    "iso:country":"TM",
    "name:rus_x_preferred":[
        "\u0411\u0435\u0440\u0437\u0435\u043d\u0433\u0438"
    ],
    "wof:name":"Berzengi",
    "wof:placetype":"locality"
},
  "geometry": {"coordinates":[58.37379,37.88527],"type":"Point"}
}