{
  "type": "Feature",
  "properties": {
    "gn:admin1_code":"05",
    "gn:asciiname":"Poskrepko",
    "gn:country_code":"TM",
    "gn:dem":790,
    "gn:feature_class":"P",
    "gn:feature_code":"PPL",
    "gn:name":"Poskrepko",
    "gn:population":0,
    "gn:timezone":"Asia/Ashgabat",
    "iso:country":"TM",
    "wof:name":"Poskrepko",
    "wof:placetype":"locality"
},
  "geometry": {"coordinates":[63.65664,36.16287],"type":"Point"}
}