{
  "type": "Feature",
  "properties": {
    "gn:admin1_code":"00",
    "gn:asciiname":"Moskva",
    "gn:country_code":"TM",
    "gn:dem":257,
    "gn:feature_class":"P",
    "gn:feature_code":"PPL",
    "gn:name":"Moskva",
    "gn:population":0,
    "gn:timezone":"Asia/Ashgabat",
    "iso:country":"TM",
    "name:und_x_variant":[
        "Yaur-Dulan",
        "Moskva"
    ],
    "wof:name":"Moskva",
    "wof:placetype":"locality"
},
  "geometry": {"coordinates":[62.3914,37.34344],"type":"Point"}
}