{
  "type": "Feature",
  "properties": {
    "gn:admin1_code":"00",
    "gn:asciiname":"Kunya-Yarmysh",
    "gn:country_code":"TM",
    "gn:dem":84,
    "gn:feature_class":"P",
    "gn:feature_code":"PPL",
    "gn:name":"Kunya-Yarmysh",
    "gn:population":0,
    "gn:timezone":"Asia/Ashgabat",
    "iso:country":"TM",
    "wof:name":"Kunya-Yarmysh",
    "wof:placetype":"locality"
},
  "geometry": {"coordinates":[59.85,41.88333],"type":"Point"}
}