{
  "type": "Feature",
  "properties": {
    "gn:admin1_code":"00",
    "gn:asciiname":"Yapach",
    "gn:country_code":"TM",
    "gn:dem":200,
    "gn:feature_class":"P",
    "gn:feature_code":"PPL",
    "gn:name":"Yapach",
    "gn:population":0,
    "gn:timezone":"Asia/Ashgabat",
    "iso:country":"TM",
    "wof:name":"Yapach",
    "wof:placetype":"locality"
},
  "geometry": {"coordinates":[63.95,38.88333],"type":"Point"}
}