{
  "type": "Feature",
  "properties": {
    "gn:admin1_code":"04",
    "gn:asciiname":"Ene-Kuliyevo",
    "gn:country_code":"TM",
    "gn:dem":175,
    "gn:feature_class":"P",
    "gn:feature_code":"PPL",
    "gn:name":"Ene-Kuliyevo",
    "gn:population":0,
    "gn:timezone":"Asia/Ashgabat",
    "iso:country":"TM",
    "wof:name":"Ene-Kuliyevo",
    "wof:placetype":"locality"
},
  "geometry": {"coordinates":[62.99454,39.31749],"type":"Point"}
}