{
  "type": "Feature",
  "properties": {
    "gn:admin1_code":"02",
    "gn:asciiname":"Magtymguly",
    "gn:country_code":"TM",
    "gn:dem":314,
    "gn:feature_class":"P",
    "gn:feature_code":"PPLA2",
    "gn:name":"Magtymguly",
    "gn:population":0,
    "gn:timezone":"Asia/Ashgabat",
    "iso:country":"TM",
    "name:hsb_x_preferred":[
        "Magtymguly"
    ],
    "name:ita_x_preferred":[
        "Garrygala"
    ],
    "name:pnb_x_preferred":[
        "\u0642\u0627\u0631\u0627 \u0642\u0644\u0639\u06c1"
    ],
    "name:rus_x_preferred":[
        "\u041a\u0430\u0440\u0430-\u041a\u0430\u043b\u0430"
    ],
    "name:rus_x_variant":[
        "\u041c\u0430\u0445\u0442\u0443\u043c\u043a\u0443\u043b\u0438"
    ],
    "name:tat_x_preferred":[
        "\u041c\u04d9\u0445\u0442\u04af\u043c\u043a\u043e\u043b\u044b\u0439"
    ],
    "name:tuk_x_preferred":[
        "Magtymguly"
    ],
    "name:und_x_variant":[
        "Kara-Kala"
    ],
    "wof:name":"Magtymguly",
    "wof:placetype":"locality"
},
  "geometry": {"coordinates":[56.28081,38.43749],"type":"Point"}
}