{
  "type": "Feature",
  "properties": {
    "gn:admin1_code":"02",
    "gn:asciiname":"Magtymguly",
    "gn:country_code":"TM",
    "gn:dem":314,
    "gn:feature_class":"P",
    "gn:feature_code":"PPLA2",
    "gn:name":"Magtymguly",
    "gn:population":0,
    "gn:timezone":"Asia/Ashgabat",
    "iso:country":"TM",
    "name:rus_x_preferred":[
        "\u041a\u0430\u0440\u0430-\u041a\u0430\u043b\u0430"
    ],
    "name:tuk_x_preferred":[
        "Magtymguly"
    ],
    "name:und_x_variant":[
        "Kara-Kala",
        "Garrygala"
    ],
    "wof:name":"Magtymguly",
    "wof:placetype":"locality"
},
  "geometry": {"coordinates":[56.28081,38.43749],"type":"Point"}
}