{
  "type": "Feature",
  "properties": {
    "gn:admin1_code":"01",
    "gn:asciiname":"Karanki",
    "gn:country_code":"TM",
    "gn:dem":622,
    "gn:feature_class":"P",
    "gn:feature_code":"PPL",
    "gn:name":"Karanki",
    "gn:population":0,
    "gn:timezone":"Asia/Ashgabat",
    "iso:country":"TM",
    "name:rus_x_preferred":[
        "\u041a\u0430\u0440\u0430\u043d\u043a\u0438"
    ],
    "wof:name":"Karanki",
    "wof:placetype":"locality"
},
  "geometry": {"coordinates":[58.31043,37.83439],"type":"Point"}
}