{
  "type": "Feature",
  "properties": {
    "gn:admin1_code":"00",
    "gn:asciiname":"Kozelkovskiy",
    "gn:country_code":"TM",
    "gn:dem":238,
    "gn:feature_class":"P",
    "gn:feature_code":"PPL",
    "gn:name":"Kozelkovskiy",
    "gn:population":0,
    "gn:timezone":"Asia/Ashgabat",
    "iso:country":"TM",
    "wof:name":"Kozelkovskiy",
    "wof:placetype":"locality"
},
  "geometry": {"coordinates":[62.16667,37.51667],"type":"Point"}
}