{
  "type": "Feature",
  "properties": {
    "gn:admin1_code":"01",
    "gn:asciiname":"Tazedurmus",
    "gn:country_code":"TM",
    "gn:dem":203,
    "gn:feature_class":"P",
    "gn:feature_code":"PPL",
    "gn:name":"T\u00e4zedurmus",
    "gn:population":0,
    "gn:timezone":"Asia/Ashgabat",
    "iso:country":"TM",
    "name:rus_x_preferred":[
        "\u0421\u043e\u0432\u0445\u043e\u0437 \u0418\u043c\u0435\u043d\u0438 \u0414\u0435\u0432\u044f\u0442\u0438 \u0410\u0448\u0445\u0430\u0431\u0430\u0434\u0441\u043a\u0438\u0445 \u041a\u043e\u043c\u0438\u0441\u0441\u0430\u0440\u043e\u0432"
    ],
    "name:tuk_x_preferred":[
        "T\u00e4zedurmus"
    ],
    "name:und_x_variant":[
        "Sovkhoz Imeni Devyati Ashkhabadskikh Komissarov"
    ],
    "wof:name":"Tazedurmus",
    "wof:placetype":"locality"
},
  "geometry": {"coordinates":[58.58545,37.93282],"type":"Point"}
}