{
  "type": "Feature",
  "properties": {
    "gn:admin1_code":"00",
    "gn:asciiname":"Zerdau",
    "gn:country_code":"TM",
    "gn:dem":510,
    "gn:feature_class":"P",
    "gn:feature_code":"PPL",
    "gn:name":"Zerdau",
    "gn:population":0,
    "gn:timezone":"Asia/Ashgabat",
    "iso:country":"TM",
    "wof:name":"Zerdau",
    "wof:placetype":"locality"
},
  "geometry": {"coordinates":[56.55,38.45],"type":"Point"}
}