{
  "type": "Feature",
  "properties": {
    "gn:admin1_code":"00",
    "gn:asciiname":"Mukry",
    "gn:country_code":"TM",
    "gn:dem":248,
    "gn:feature_class":"P",
    "gn:feature_code":"PPL",
    "gn:name":"Mukry",
    "gn:population":0,
    "gn:timezone":"Asia/Ashgabat",
    "iso:country":"TM",
    "name:und_x_variant":[
        "Mukri",
        "Mukry"
    ],
    "wof:name":"Mukry",
    "wof:placetype":"locality"
},
  "geometry": {"coordinates":[65.51666999999999,37.65],"type":"Point"}
}