{
  "type": "Feature",
  "properties": {
    "gn:admin1_code":"00",
    "gn:asciiname":"Byr-Koz",
    "gn:country_code":"TM",
    "gn:dem":223,
    "gn:feature_class":"P",
    "gn:feature_code":"PPL",
    "gn:name":"Byr-Koz",
    "gn:population":0,
    "gn:timezone":"Asia/Ashgabat",
    "iso:country":"TM",
    "wof:name":"Byr-Koz",
    "wof:placetype":"locality"
},
  "geometry": {"coordinates":[61.86666999999999,37.51667],"type":"Point"}
}