{
  "type": "Feature",
  "properties": {
    "gn:admin1_code":"00",
    "gn:asciiname":"Kuvak",
    "gn:country_code":"TM",
    "gn:dem":253,
    "gn:feature_class":"P",
    "gn:feature_code":"PPL",
    "gn:name":"Kuvak",
    "gn:population":0,
    "gn:timezone":"Asia/Ashgabat",
    "iso:country":"TM",
    "wof:name":"Kuvak",
    "wof:placetype":"locality"
},
  "geometry": {"coordinates":[65.58333,37.58333],"type":"Point"}
}