{
  "type": "Feature",
  "properties": {
    "gn:admin1_code":"00",
    "gn:asciiname":"Imeni Tel'mana",
    "gn:country_code":"TM",
    "gn:dem":88,
    "gn:feature_class":"P",
    "gn:feature_code":"PPL",
    "gn:name":"Imeni Tel\u2019mana",
    "gn:population":0,
    "gn:timezone":"Asia/Ashgabat",
    "iso:country":"TM",
    "wof:name":"Imeni Tel'mana",
    "wof:placetype":"locality"
},
  "geometry": {"coordinates":[59.98333,41.53333],"type":"Point"}
}