{
  "type": "Feature",
  "properties": {
    "gn:admin1_code":"00",
    "gn:asciiname":"Permet",
    "gn:country_code":"TM",
    "gn:dem":197,
    "gn:feature_class":"P",
    "gn:feature_code":"PPL",
    "gn:name":"Permet",
    "gn:population":0,
    "gn:timezone":"Asia/Ashgabat",
    "iso:country":"TM",
    "wof:name":"Permet",
    "wof:placetype":"locality"
},
  "geometry": {"coordinates":[61.56667,37.81667],"type":"Point"}
}