{
  "type": "Feature",
  "properties": {
    "gn:admin1_code":"00",
    "gn:asciiname":"Pioner",
    "gn:country_code":"TM",
    "gn:dem":196,
    "gn:feature_class":"P",
    "gn:feature_code":"PPL",
    "gn:name":"Pioner",
    "gn:population":0,
    "gn:timezone":"Asia/Ashgabat",
    "iso:country":"TM",
    "name:bul_x_preferred":[
        "\u041f\u0438\u043e\u043d\u0435\u0440"
    ],
    "name:cat_x_preferred":[
        "Pioner"
    ],
    "name:ceb_x_preferred":[
        "Pioner"
    ],
    "name:deu_x_preferred":[
        "Pioner"
    ],
    "name:kaz_x_preferred":[
        "\u041f\u0438\u043e\u043d\u0435\u0440"
    ],
    "name:nor_x_preferred":[
        "Pioner"
    ],
    "name:rus_x_preferred":[
        "\u041f\u0438\u043e\u043d\u0435\u0440"
    ],
    "name:swe_x_preferred":[
        "Pioner"
    ],
    "name:ukr_x_preferred":[
        "\u041f\u0456\u043e\u043d\u0435\u0440"
    ],
    "name:und_x_variant":[
        "Kuchchi",
        "Pioner"
    ],
    "wof:name":"Pioner",
    "wof:placetype":"locality"
},
  "geometry": {"coordinates":[63.78439,38.88674],"type":"Point"}
}