{
  "type": "Feature",
  "properties": {
    "gn:admin1_code":"00",
    "gn:asciiname":"Pioner",
    "gn:country_code":"TM",
    "gn:dem":196,
    "gn:feature_class":"P",
    "gn:feature_code":"PPL",
    "gn:name":"Pioner",
    "gn:population":0,
    "gn:timezone":"Asia/Ashgabat",
    "iso:country":"TM",
    "name:und_x_variant":[
        "Kuchchi",
        "Pioner"
    ],
    "wof:name":"Pioner",
    "wof:placetype":"locality"
},
  "geometry": {"coordinates":[63.78439,38.88674],"type":"Point"}
}