{
  "type": "Feature",
  "properties": {
    "gn:admin1_code":"00",
    "gn:asciiname":"Yashguch",
    "gn:country_code":"TM",
    "gn:dem":197,
    "gn:feature_class":"P",
    "gn:feature_code":"PPL",
    "gn:name":"Yashguch",
    "gn:population":0,
    "gn:timezone":"Asia/Ashgabat",
    "iso:country":"TM",
    "wof:name":"Yashguch",
    "wof:placetype":"locality"
},
  "geometry": {"coordinates":[60.63333000000001,37.26667],"type":"Point"}
}