{
  "type": "Feature",
  "properties": {
    "gn:admin1_code":"02",
    "gn:asciiname":"Agach-Arvat",
    "gn:country_code":"TM",
    "gn:dem":32,
    "gn:feature_class":"P",
    "gn:feature_code":"PPL",
    "gn:name":"Agach-Arvat",
    "gn:population":0,
    "gn:timezone":"Asia/Ashgabat",
    "iso:country":"TM",
    "name:rus_x_preferred":[
        "\u0410\u0433\u0430\u0447-\u0410\u0440\u0432\u0430\u0442"
    ],
    "wof:name":"Agach-Arvat",
    "wof:placetype":"locality"
},
  "geometry": {"coordinates":[54.78339,37.70119],"type":"Point"}
}