{
  "type": "Feature",
  "properties": {
    "gn:admin1_code":"01",
    "gn:asciiname":"Kasy",
    "gn:country_code":"TM",
    "gn:dem":121,
    "gn:feature_class":"P",
    "gn:feature_code":"PPL",
    "gn:name":"Kasy",
    "gn:population":0,
    "gn:timezone":"Asia/Ashgabat",
    "iso:country":"TM",
    "name:rus_x_preferred":[
        "\u041a\u0430\u0441\u044b"
    ],
    "name:tuk_x_preferred":[
        "Gysy"
    ],
    "wof:name":"Kasy",
    "wof:placetype":"locality"
},
  "geometry": {"coordinates":[58.95002,38.00909],"type":"Point"}
}