{
  "type": "Feature",
  "properties": {
    "gn:admin1_code":"00",
    "gn:asciiname":"Yaskha",
    "gn:country_code":"TM",
    "gn:dem":-8,
    "gn:feature_class":"P",
    "gn:feature_code":"PPL",
    "gn:name":"Yaskha",
    "gn:population":0,
    "gn:timezone":"Asia/Ashgabat",
    "iso:country":"TM",
    "name:und_x_variant":[
        "Yaskhan",
        "Yaskha"
    ],
    "wof:name":"Yaskha",
    "wof:placetype":"locality"
},
  "geometry": {"coordinates":[55.55863000000001,39.70921],"type":"Point"}
}