{
  "type": "Feature",
  "properties": {
    "iso:country":"TM",
    "name:cat_x_preferred":[
        "G\u00f6k Tepe"
    ],
    "name:eng_x_preferred":[
        "Geok Tepe"
    ],
    "name:est_x_preferred":[
        "G\u00f6kdepe"
    ],
    "name:fas_x_preferred":[
        "\u06af\u0648\u06af\u200c\u062a\u067e\u0647"
    ],
    "name:fin_x_preferred":[
        "Geok-Tepe"
    ],
    "name:fra_x_preferred":[
        "G\u00f6kdepe"
    ],
    "name:hsb_x_preferred":[
        "G\u00f6kdepe"
    ],
    "name:ita_x_preferred":[
        "Geok Tepe"
    ],
    "name:jpn_x_preferred":[
        "\u30ae\u30e7\u30af\u30c6\u30da"
    ],
    "name:lit_x_preferred":[
        "Geok Tep\u0117"
    ],
    "name:nld_x_preferred":[
        "Geok-Tepe"
    ],
    "name:pnb_x_preferred":[
        "\u06af\u0648\u06a9 \u062a\u067e\u06c1"
    ],
    "name:pol_x_preferred":[
        "G\u00f6kdepe"
    ],
    "name:rus_x_preferred":[
        "\u0413\u0435\u043e\u043a-\u0422\u0435\u043f\u0435"
    ],
    "name:rus_x_variant":[
        "\u0413\u0451\u043a\u0434\u0435\u043f\u0435"
    ],
    "name:spa_x_preferred":[
        "G\u00f6kdepe"
    ],
    "name:tat_x_preferred":[
        "\u041a\u04af\u043a\u0442\u04af\u0431\u04d9"
    ],
    "name:tuk_x_preferred":[
        "G\u00f6kdepe ur\u015fy"
    ],
    "name:tur_x_preferred":[
        "G\u00f6ktepe Sava\u015f\u0131"
    ],
    "name:unk_x_variant":[
        "Geok-Tepe"
    ],
    "qs:gn_country":"TM",
    "qs:gn_fcode":"PPL",
    "qs:gn_pop":0,
    "qs:name":"G\u00f6kdepe",
    "qs:name_adm0":"Turkmenistan",
    "qs:name_adm1":"Ashkhabad",
    "qs:photos":6,
    "qs:photos_1k":1,
    "qs:photos_9k":1,
    "qs:photos_9r":1,
    "qs:photos_all":6,
    "qs:photos_sr":1,
    "qs:placetype":"Town",
    "qs:pop_sr":"0",
    "qs:woe_adm0":23424972,
    "wof:name":"G\u00f6kdepe",
    "wof:placetype":"locality"
},
  "geometry": {"coordinates":[57.96072,38.15863],"type":"Point"}
}