{
  "type": "Feature",
  "properties": {
    "gn:admin1_code":"00",
    "gn:asciiname":"Tamykli",
    "gn:country_code":"TM",
    "gn:dem":17,
    "gn:feature_class":"P",
    "gn:feature_code":"PPL",
    "gn:name":"Tamykli",
    "gn:population":0,
    "gn:timezone":"Asia/Ashgabat",
    "iso:country":"TM",
    "name:und_x_variant":[
        "Tamykly",
        "Tamykli"
    ],
    "wof:name":"Tamykli",
    "wof:placetype":"locality"
},
  "geometry": {"coordinates":[55.37378,39.3913],"type":"Point"}
}