{
  "type": "Feature",
  "properties": {
    "gn:admin1_code":"04",
    "gn:asciiname":"Sakar",
    "gn:country_code":"TM",
    "gn:dem":196,
    "gn:feature_class":"P",
    "gn:feature_code":"PPL",
    "gn:name":"S\u00e4kar",
    "gn:population":0,
    "gn:timezone":"Asia/Ashgabat",
    "iso:country":"TM",
    "name:und_x_variant":[
        "Bazar-Sakar",
        "S\u00e4kar"
    ],
    "wof:name":"Sakar",
    "wof:placetype":"locality"
},
  "geometry": {"coordinates":[63.74338,38.92577],"type":"Point"}
}