{
  "type": "Feature",
  "properties": {
    "gn:admin1_code":"01",
    "gn:asciiname":"Makhmaldepe",
    "gn:country_code":"TM",
    "gn:dem":281,
    "gn:feature_class":"P",
    "gn:feature_code":"PPL",
    "gn:name":"Makhmaldepe",
    "gn:population":0,
    "gn:timezone":"Asia/Ashgabat",
    "iso:country":"TM",
    "name:tuk_x_preferred":[
        "Mahmal"
    ],
    "name:und_x_variant":[
        "Makhmal",
        "Makhmal-Tepe",
        "Makhmaldepe"
    ],
    "wof:name":"Makhmaldepe",
    "wof:placetype":"locality"
},
  "geometry": {"coordinates":[60.2469,36.96577],"type":"Point"}
}