{
  "type": "Feature",
  "properties": {
    "gn:admin1_code":"02",
    "gn:asciiname":"Gurruk",
    "gn:country_code":"TM",
    "gn:dem":-18,
    "gn:feature_class":"P",
    "gn:feature_code":"PPL",
    "gn:name":"Gurruk",
    "gn:population":0,
    "gn:timezone":"Asia/Ashgabat",
    "iso:country":"TM",
    "name:tuk_x_preferred":[
        "Gurruk"
    ],
    "wof:name":"Gurruk",
    "wof:placetype":"locality"
},
  "geometry": {"coordinates":[54.07406,37.68025],"type":"Point"}
}