{
  "type": "Feature",
  "properties": {
    "gn:admin1_code":"04",
    "gn:asciiname":"El'jik",
    "gn:country_code":"TM",
    "gn:dem":176,
    "gn:feature_class":"P",
    "gn:feature_code":"PPL",
    "gn:name":"El\u2019jik",
    "gn:population":0,
    "gn:timezone":"Asia/Ashgabat",
    "iso:country":"TM",
    "name:und_x_variant":[
        "El\u2019dzhin",
        "Il\u2019dzhik",
        "Iljik",
        "El\u2019dzhik",
        "El\u2019jik"
    ],
    "wof:name":"El'jik",
    "wof:placetype":"locality"
},
  "geometry": {"coordinates":[62.98761999999999,39.4143],"type":"Point"}
}