{
  "type": "Feature",
  "properties": {
    "gn:admin1_code":"00",
    "gn:asciiname":"Isrikkala",
    "gn:country_code":"TM",
    "gn:dem":83,
    "gn:feature_class":"P",
    "gn:feature_code":"PPL",
    "gn:name":"Isrikkala",
    "gn:population":0,
    "gn:timezone":"Asia/Ashgabat",
    "iso:country":"TM",
    "wof:name":"Isrikkala",
    "wof:placetype":"locality"
},
  "geometry": {"coordinates":[59.83333,41.85],"type":"Point"}
}