{
  "type": "Feature",
  "properties": {
    "gn:admin1_code":"00",
    "gn:asciiname":"Shikhzyab",
    "gn:cc2":"TM",
    "gn:country_code":"TM",
    "gn:dem":73,
    "gn:feature_class":"P",
    "gn:feature_code":"PPL",
    "gn:name":"Shikhzyab",
    "gn:population":0,
    "gn:timezone":"Asia/Ashgabat",
    "iso:country":"TM",
    "name:und_x_variant":[
        "Shikh\u2019yab",
        "Shikhzyab"
    ],
    "wof:name":"Shikhzyab",
    "wof:placetype":"locality"
},
  "geometry": {"coordinates":[59.43333000000001,42.23333],"type":"Point"}
}