{
  "type": "Feature",
  "properties": {
    "gn:admin1_code":"00",
    "gn:asciiname":"Komsomol",
    "gn:country_code":"TM",
    "gn:dem":238,
    "gn:feature_class":"P",
    "gn:feature_code":"PPL",
    "gn:name":"Komsomol",
    "gn:population":0,
    "gn:timezone":"Asia/Ashgabat",
    "iso:country":"TM",
    "name:und_x_variant":[
        "Yel-Bars",
        "Komsomol"
    ],
    "wof:name":"Komsomol",
    "wof:placetype":"locality"
},
  "geometry": {"coordinates":[62.09627,37.46986],"type":"Point"}
}