{
  "type": "Feature",
  "properties": {
    "gn:admin1_code":"00",
    "gn:asciiname":"Komsomol",
    "gn:country_code":"TM",
    "gn:dem":238,
    "gn:feature_class":"P",
    "gn:feature_code":"PPL",
    "gn:name":"Komsomol",
    "gn:population":0,
    "gn:timezone":"Asia/Ashgabat",
    "iso:country":"TM",
    "name:afr_x_preferred":[
        "Komsomol"
    ],
    "name:ara_x_preferred":[
        "\u0643\u0645\u0633\u0645\u0648\u0644"
    ],
    "name:ast_x_preferred":[
        "Komsomol"
    ],
    "name:aze_x_preferred":[
        "Komsomol"
    ],
    "name:bel_x_preferred":[
        "\u041a\u0430\u043c\u0441\u0430\u043c\u043e\u043b"
    ],
    "name:bul_x_preferred":[
        "\u041a\u043e\u043c\u0441\u043e\u043c\u043e\u043b"
    ],
    "name:cat_x_preferred":[
        "Komsomol"
    ],
    "name:ces_x_preferred":[
        "Komsomol"
    ],
    "name:dan_x_preferred":[
        "Komsomol"
    ],
    "name:deu_x_preferred":[
        "Komsomol"
    ],
    "name:ell_x_preferred":[
        "\u039a\u03bf\u03bc\u03c3\u03bf\u03bc\u03cc\u03bb"
    ],
    "name:epo_x_preferred":[
        "Komsomolo"
    ],
    "name:est_x_preferred":[
        "Komsomol"
    ],
    "name:eus_x_preferred":[
        "Komsomol"
    ],
    "name:fas_x_preferred":[
        "\u06a9\u0648\u0645\u0633\u0648\u0645\u0648\u0644"
    ],
    "name:fin_x_preferred":[
        "Komsomol"
    ],
    "name:fra_x_preferred":[
        "Komsomol"
    ],
    "name:heb_x_preferred":[
        "\u05e7\u05d5\u05de\u05e1\u05d5\u05de\u05d5\u05dc"
    ],
    "name:hrv_x_preferred":[
        "Komsomol"
    ],
    "name:hun_x_preferred":[
        "Komszomol"
    ],
    "name:hye_x_preferred":[
        "\u053f\u0565\u0576\u057f\u0580\u0578\u0576\u0561\u056f\u0561\u0576 \u056f\u0578\u0574\u056b\u057f\u0565"
    ],
    "name:ind_x_preferred":[
        "Komsomol"
    ],
    "name:ita_x_preferred":[
        "Komsomol"
    ],
    "name:jpn_x_preferred":[
        "\u30b3\u30e0\u30bd\u30e2\u30fc\u30eb"
    ],
    "name:kat_x_preferred":[
        "\u10d9\u10dd\u10db\u10d9\u10d0\u10d5\u10e8\u10d8\u10e0\u10d8"
    ],
    "name:lav_x_preferred":[
        "Komjaunatne"
    ],
    "name:lit_x_preferred":[
        "Komjaunimas"
    ],
    "name:ltz_x_preferred":[
        "Komsomol"
    ],
    "name:nld_x_preferred":[
        "Komsomol"
    ],
    "name:nor_x_preferred":[
        "Komsomol"
    ],
    "name:oss_x_preferred":[
        "\u0424\u00e6\u0441\u043a\u043e\u043c\u0446\u00e6\u0434\u0438\u0441"
    ],
    "name:pol_x_preferred":[
        "Komsomo\u0142"
    ],
    "name:por_x_preferred":[
        "Komsomol"
    ],
    "name:ron_x_preferred":[
        "Comsomol"
    ],
    "name:sco_x_preferred":[
        "Komsomol"
    ],
    "name:slk_x_preferred":[
        "Komsomol"
    ],
    "name:slv_x_preferred":[
        "Komsomol"
    ],
    "name:spa_x_preferred":[
        "Komsomol"
    ],
    "name:srp_x_preferred":[
        "\u041a\u043e\u043c\u0441\u043e\u043c\u043e\u043b"
    ],
    "name:swe_x_preferred":[
        "Komsomol"
    ],
    "name:tat_x_preferred":[
        "\u041a\u043e\u043c\u0441\u043e\u043c\u043e\u043b"
    ],
    "name:tur_x_preferred":[
        "Komsomol"
    ],
    "name:ukr_x_preferred":[
        "\u041a\u043e\u043c\u0441\u043e\u043c\u043e\u043b"
    ],
    "name:und_x_variant":[
        "Yel-Bars"
    ],
    "name:vie_x_preferred":[
        "Komsomol"
    ],
    "name:zho_x_preferred":[
        "\u5168\u8054\u76df\u5217\u5b81\u4e3b\u4e49\u9752\u5e74\u5171\u4ea7\u4e3b\u4e49\u8054\u76df"
    ],
    "wof:name":"Komsomol",
    "wof:placetype":"locality"
},
  "geometry": {"coordinates":[62.09627,37.46986],"type":"Point"}
}