{
  "type": "Feature",
  "properties": {
    "gn:admin1_code":"00",
    "gn:asciiname":"Grodekovskiy",
    "gn:cc2":"TM",
    "gn:country_code":"TM",
    "gn:dem":238,
    "gn:feature_class":"P",
    "gn:feature_code":"PPL",
    "gn:name":"Grodekovskiy",
    "gn:population":0,
    "gn:timezone":"Asia/Ashgabat",
    "iso:country":"TM",
    "name:und_x_variant":[
        "Gordikovskiy",
        "Grodekovskiy"
    ],
    "wof:name":"Grodekovskiy",
    "wof:placetype":"locality"
},
  "geometry": {"coordinates":[62.18333000000001,37.55],"type":"Point"}
}