{
  "type": "Feature",
  "properties": {
    "gn:admin1_code":"01",
    "gn:asciiname":"Begi-Sakar",
    "gn:country_code":"TM",
    "gn:dem":265,
    "gn:feature_class":"P",
    "gn:feature_code":"PPL",
    "gn:name":"Begi-Sakar",
    "gn:population":0,
    "gn:timezone":"Asia/Ashgabat",
    "iso:country":"TM",
    "wof:name":"Begi-Sakar",
    "wof:placetype":"locality"
},
  "geometry": {"coordinates":[61.35,36.53333],"type":"Point"}
}