{
  "type": "Feature",
  "properties": {
    "gn:admin1_code":"02",
    "gn:asciiname":"Jashan",
    "gn:country_code":"TM",
    "gn:dem":33,
    "gn:feature_class":"P",
    "gn:feature_code":"PPL",
    "gn:name":"Jashan",
    "gn:population":0,
    "gn:timezone":"Asia/Ashgabat",
    "iso:country":"TM",
    "wof:name":"Jashan",
    "wof:placetype":"locality"
},
  "geometry": {"coordinates":[55.56667,39.68333],"type":"Point"}
}