{
  "type": "Feature",
  "properties": {
    "gn:admin1_code":"00",
    "gn:asciiname":"Imeni Kalinina",
    "gn:cc2":"TM",
    "gn:country_code":"TM",
    "gn:dem":272,
    "gn:feature_class":"P",
    "gn:feature_code":"PPL",
    "gn:name":"Imeni Kalinina",
    "gn:population":0,
    "gn:timezone":"Asia/Ashgabat",
    "iso:country":"TM",
    "name:kir_x_preferred":[
        "\u041a\u0430\u043b\u0438\u043d\u0438\u043d"
    ],
    "name:und_x_variant":[
        "Kyzyl",
        "Imeni Kalinina"
    ],
    "name:uzb_x_preferred":[
        "Kalinin"
    ],
    "wof:name":"Imeni Kalinina",
    "wof:placetype":"locality"
},
  "geometry": {"coordinates":[62.46666999999999,37.03333],"type":"Point"}
}