{
  "type": "Feature",
  "properties": {
    "gn:admin1_code":"00",
    "gn:asciiname":"Bangil'dy",
    "gn:country_code":"TM",
    "gn:dem":193,
    "gn:feature_class":"P",
    "gn:feature_code":"PPL",
    "gn:name":"Bangil\u2019dy",
    "gn:population":0,
    "gn:timezone":"Asia/Ashgabat",
    "iso:country":"TM",
    "wof:name":"Bangil'dy",
    "wof:placetype":"locality"
},
  "geometry": {"coordinates":[63.63333000000001,39.01667],"type":"Point"}
}