{
  "type": "Feature",
  "properties": {
    "gn:admin1_code":"02",
    "gn:asciiname":"Madaw",
    "gn:country_code":"TM",
    "gn:dem":20,
    "gn:feature_class":"P",
    "gn:feature_code":"PPL",
    "gn:name":"Madaw",
    "gn:population":0,
    "gn:timezone":"Asia/Ashgabat",
    "iso:country":"TM",
    "name:rus_x_preferred":[
        "\u041c\u0430\u0434\u0430\u0443"
    ],
    "name:und_x_variant":[
        "Madau",
        "Madav",
        "Madaw"
    ],
    "wof:name":"Madaw",
    "wof:placetype":"locality"
},
  "geometry": {"coordinates":[54.74406,38.14046],"type":"Point"}
}