{
  "type": "Feature",
  "properties": {
    "gn:admin1_code":"00",
    "gn:asciiname":"Teze-Yel",
    "gn:country_code":"TM",
    "gn:dem":235,
    "gn:feature_class":"P",
    "gn:feature_code":"PPL",
    "gn:name":"Teze-Y\u00ebl",
    "gn:population":0,
    "gn:timezone":"Asia/Ashgabat",
    "iso:country":"TM",
    "name:und_x_variant":[
        "Azat",
        "Teze-Y\u00ebl"
    ],
    "wof:name":"Teze-Yel",
    "wof:placetype":"locality"
},
  "geometry": {"coordinates":[62.25728,37.62138],"type":"Point"}
}