{
  "type": "Feature",
  "properties": {
    "gn:admin1_code":"00",
    "gn:asciiname":"Il'chik",
    "gn:country_code":"TM",
    "gn:dem":179,
    "gn:feature_class":"P",
    "gn:feature_code":"PPL",
    "gn:name":"Il\u2019chik",
    "gn:population":0,
    "gn:timezone":"Asia/Ashgabat",
    "iso:country":"TM",
    "wof:name":"Il'chik",
    "wof:placetype":"locality"
},
  "geometry": {"coordinates":[62.98333,39.38333],"type":"Point"}
}