{
  "type": "Feature",
  "properties": {
    "gn:admin1_code":"04",
    "gn:asciiname":"Khatab",
    "gn:country_code":"TM",
    "gn:dem":252,
    "gn:feature_class":"P",
    "gn:feature_code":"PPL",
    "gn:name":"Khatab",
    "gn:population":0,
    "gn:timezone":"Asia/Ashgabat",
    "iso:country":"TM",
    "name:und_x_variant":[
        "Khatap",
        "Khatab"
    ],
    "wof:name":"Khatab",
    "wof:placetype":"locality"
},
  "geometry": {"coordinates":[65.52889,37.62336],"type":"Point"}
}