{
  "type": "Feature",
  "properties": {
    "gn:admin1_code":"00",
    "gn:asciiname":"Kara-Tepe",
    "gn:country_code":"TM",
    "gn:dem":695,
    "gn:feature_class":"P",
    "gn:feature_code":"PPL",
    "gn:name":"Kara-Tepe",
    "gn:population":0,
    "gn:timezone":"Asia/Ashgabat",
    "iso:country":"TM",
    "wof:name":"Kara-Tepe",
    "wof:placetype":"locality"
},
  "geometry": {"coordinates":[62.28333000000001,35.26667],"type":"Point"}
}