{
  "type": "Feature",
  "properties": {
    "gn:admin1_code":"00",
    "gn:asciiname":"Burguchi",
    "gn:country_code":"TM",
    "gn:dem":247,
    "gn:feature_class":"P",
    "gn:feature_code":"PPL",
    "gn:name":"Burguchi",
    "gn:population":0,
    "gn:timezone":"Asia/Ashgabat",
    "iso:country":"TM",
    "wof:name":"Burguchi",
    "wof:placetype":"locality"
},
  "geometry": {"coordinates":[65.41271,37.73174],"type":"Point"}
}