{
  "type": "Feature",
  "properties": {
    "gn:admin1_code":"04",
    "gn:asciiname":"Yaroshevskiy",
    "gn:country_code":"TM",
    "gn:dem":269,
    "gn:feature_class":"P",
    "gn:feature_code":"PPL",
    "gn:name":"Yaroshevskiy",
    "gn:population":0,
    "gn:timezone":"Asia/Ashgabat",
    "iso:country":"TM",
    "wof:name":"Yaroshevskiy",
    "wof:placetype":"locality"
},
  "geometry": {"coordinates":[64.87479,37.24785],"type":"Point"}
}