{
  "type": "Feature",
  "properties": {
    "gn:admin1_code":"00",
    "gn:asciiname":"Beuradzhi",
    "gn:country_code":"TM",
    "gn:dem":7,
    "gn:feature_class":"P",
    "gn:feature_code":"PPL",
    "gn:name":"Beuradzhi",
    "gn:population":0,
    "gn:timezone":"Asia/Ashgabat",
    "iso:country":"TM",
    "wof:name":"Beuradzhi",
    "wof:placetype":"locality"
},
  "geometry": {"coordinates":[55.13333000000001,39.61667],"type":"Point"}
}