{
  "type": "Feature",
  "properties": {
    "gn:admin1_code":"00",
    "gn:asciiname":"Bokurdak",
    "gn:country_code":"TM",
    "gn:dem":84,
    "gn:feature_class":"P",
    "gn:feature_code":"PPL",
    "gn:name":"Bokurdak",
    "gn:population":0,
    "gn:timezone":"Asia/Ashgabat",
    "iso:country":"TM",
    "name:und_x_variant":[
        "Bakhardok",
        "Bokhurdok",
        "Bokurdak"
    ],
    "wof:name":"Bokurdak",
    "wof:placetype":"locality"
},
  "geometry": {"coordinates":[58.49269,38.76307],"type":"Point"}
}