{
  "type": "Feature",
  "properties": {
    "gn:admin1_code":"00",
    "gn:asciiname":"Bagt",
    "gn:country_code":"TM",
    "gn:dem":230,
    "gn:feature_class":"P",
    "gn:feature_code":"PPL",
    "gn:name":"Bagt",
    "gn:population":0,
    "gn:timezone":"Asia/Ashgabat",
    "iso:country":"TM",
    "wof:name":"Bagt",
    "wof:placetype":"locality"
},
  "geometry": {"coordinates":[62.18333000000001,37.66667],"type":"Point"}
}