{
  "type": "Feature",
  "properties": {
    "gn:admin1_code":"00",
    "gn:asciiname":"Sheykh",
    "gn:country_code":"TM",
    "gn:dem":195,
    "gn:feature_class":"P",
    "gn:feature_code":"PPL",
    "gn:name":"Sheykh",
    "gn:population":0,
    "gn:timezone":"Asia/Ashgabat",
    "iso:country":"TM",
    "wof:name":"Sheykh",
    "wof:placetype":"locality"
},
  "geometry": {"coordinates":[63.75,38.98333],"type":"Point"}
}