{
  "type": "Feature",
  "properties": {
    "gn:admin1_code":"00",
    "gn:asciiname":"Bashvak",
    "gn:country_code":"TM",
    "gn:dem":216,
    "gn:feature_class":"P",
    "gn:feature_code":"PPL",
    "gn:name":"Bashvak",
    "gn:population":0,
    "gn:timezone":"Asia/Ashgabat",
    "iso:country":"TM",
    "wof:name":"Bashvak",
    "wof:placetype":"locality"
},
  "geometry": {"coordinates":[64.43333,38.38333],"type":"Point"}
}