{
  "type": "Feature",
  "properties": {
    "gn:admin1_code":"00",
    "gn:asciiname":"Tang-Kotan",
    "gn:country_code":"TM",
    "gn:dem":923,
    "gn:feature_class":"P",
    "gn:feature_code":"PPL",
    "gn:name":"Tang-Kotan",
    "gn:population":0,
    "gn:timezone":"Asia/Ashgabat",
    "iso:country":"TM",
    "wof:name":"Tang-Kotan",
    "wof:placetype":"locality"
},
  "geometry": {"coordinates":[66.36686999999999,37.89731],"type":"Point"}
}