{
  "type": "Feature",
  "properties": {
    "gn:admin1_code":"00",
    "gn:asciiname":"Chupli",
    "gn:country_code":"TM",
    "gn:dem":190,
    "gn:feature_class":"P",
    "gn:feature_code":"PPL",
    "gn:name":"Chupli",
    "gn:population":0,
    "gn:timezone":"Asia/Ashgabat",
    "iso:country":"TM",
    "wof:name":"Chupli",
    "wof:placetype":"locality"
},
  "geometry": {"coordinates":[63.53333000000001,39.06667],"type":"Point"}
}