{
  "type": "Feature",
  "properties": {
    "gn:admin1_code":"00",
    "gn:asciiname":"Sukhty Pervyy",
    "gn:country_code":"TM",
    "gn:dem":236,
    "gn:feature_class":"P",
    "gn:feature_code":"PPL",
    "gn:name":"Sukhty Pervyy",
    "gn:population":0,
    "gn:timezone":"Asia/Ashgabat",
    "iso:country":"TM",
    "wof:name":"Sukhty Pervyy",
    "wof:placetype":"locality"
},
  "geometry": {"coordinates":[62.01667,37.43333],"type":"Point"}
}