{
  "type": "Feature",
  "properties": {
    "gn:admin1_code":"01",
    "gn:asciiname":"Ahal",
    "gn:country_code":"TM",
    "gn:dem":155,
    "gn:feature_class":"P",
    "gn:feature_code":"PPL",
    "gn:name":"Ahal",
    "gn:population":0,
    "gn:timezone":"Asia/Ashgabat",
    "iso:country":"TM",
    "name:fas_x_preferred":[
        "\u0622\u062e\u0627\u0644"
    ],
    "name:nld_x_preferred":[
        "Ahal"
    ],
    "name:rus_x_preferred":[
        "\u0411\u0438\u0440\u043b\u0435\u0448\u0438\u043a \u041f\u0435\u0440\u0432\u044b\u0439"
    ],
    "name:tuk_x_preferred":[
        "Ahal"
    ],
    "name:und_x_variant":[
        "Orta-Yaylya",
        "Birlyashik Pervyy",
        "Birlyashik",
        "Birleshik Pervyy"
    ],
    "wof:name":"Ahal",
    "wof:placetype":"locality"
},
  "geometry": {"coordinates":[58.01605,38.21978],"type":"Point"}
}