{
  "type": "Feature",
  "properties": {
    "gn:admin1_code":"02",
    "gn:asciiname":"Alaja",
    "gn:cc2":"TM",
    "gn:country_code":"TM",
    "gn:dem":-25,
    "gn:feature_class":"P",
    "gn:feature_code":"PPL",
    "gn:name":"Alaja",
    "gn:population":0,
    "gn:timezone":"Asia/Ashgabat",
    "iso:country":"TM",
    "name:und_x_variant":[
        "Aladzha",
        "Alaja"
    ],
    "wof:name":"Alaja",
    "wof:placetype":"locality"
},
  "geometry": {"coordinates":[53.21222,39.35694],"type":"Point"}
}