{
  "type": "Feature",
  "properties": {
    "gn:admin1_code":"00",
    "gn:asciiname":"Zergumen",
    "gn:country_code":"TM",
    "gn:dem":182,
    "gn:feature_class":"P",
    "gn:feature_code":"PPL",
    "gn:name":"Zergumen",
    "gn:population":0,
    "gn:timezone":"Asia/Ashgabat",
    "iso:country":"TM",
    "wof:name":"Zergumen",
    "wof:placetype":"locality"
},
  "geometry": {"coordinates":[63.26667,39.26667],"type":"Point"}
}