{
  "type": "Feature",
  "properties": {
    "gn:admin1_code":"00",
    "gn:asciiname":"Koshakak",
    "gn:country_code":"TM",
    "gn:dem":67,
    "gn:feature_class":"P",
    "gn:feature_code":"PPL",
    "gn:name":"Koshakak",
    "gn:population":0,
    "gn:timezone":"Asia/Ashgabat",
    "iso:country":"TM",
    "wof:name":"Koshakak",
    "wof:placetype":"locality"
},
  "geometry": {"coordinates":[57.78785,38.80095],"type":"Point"}
}