{
  "type": "Feature",
  "properties": {
    "gn:gn_country":"TM",
    "gn:gn_fcode":"PPL",
    "gn:gn_pop":27526,
    "gn:population":27526,
    "iso:country":"TM",
    "name:ara_x_preferred":[
        "\u0623\u0646\u0627\u0648"
    ],
    "name:bar_x_preferred":[
        "\u00c4new"
    ],
    "name:bul_x_preferred":[
        "\u0410\u043d\u0430\u0443"
    ],
    "name:cat_x_preferred":[
        "Anau"
    ],
    "name:deu_x_preferred":[
        "\u00c4new"
    ],
    "name:eng_x_preferred":[
        "Anau"
    ],
    "name:epo_x_preferred":[
        "Annau"
    ],
    "name:est_x_preferred":[
        "\u00c4new"
    ],
    "name:fas_x_preferred":[
        "\u0627\u0646\u0627\u0626\u0648"
    ],
    "name:fra_x_preferred":[
        "\u00c4new"
    ],
    "name:hin_x_preferred":[
        "\u0906\u0928\u0947\u0909"
    ],
    "name:hye_x_preferred":[
        "\u0531\u0576\u0576\u0561\u0578\u0582"
    ],
    "name:ind_x_preferred":[
        "Anau"
    ],
    "name:ita_x_preferred":[
        "\u00c4new"
    ],
    "name:jpn_x_preferred":[
        "\u30a2\u30ca\u30a6"
    ],
    "name:kat_x_preferred":[
        "\u10d0\u10dc\u10d0\u10e3"
    ],
    "name:kor_x_preferred":[
        "\uc544\ub098\uc6b0"
    ],
    "name:lit_x_preferred":[
        "Anau"
    ],
    "name:nld_x_preferred":[
        "Anau"
    ],
    "name:pnb_x_preferred":[
        "\u0627\u0646\u0627\u0624"
    ],
    "name:pol_x_preferred":[
        "\u00c4new"
    ],
    "name:por_x_preferred":[
        "Anev"
    ],
    "name:ron_x_preferred":[
        "\u00c4new"
    ],
    "name:rup_x_preferred":[
        "Anau"
    ],
    "name:rus_x_preferred":[
        "\u0410\u043d\u043d\u0430\u0443"
    ],
    "name:sco_x_preferred":[
        "Anau"
    ],
    "name:spa_x_preferred":[
        "Annau"
    ],
    "name:sqi_x_preferred":[
        "\u00c4new"
    ],
    "name:srp_x_preferred":[
        "\u0410\u043d\u0430\u0443"
    ],
    "name:swe_x_preferred":[
        "\u00c4nev"
    ],
    "name:tuk_x_preferred":[
        "\u00c4new"
    ],
    "name:tur_x_preferred":[
        "Anav K\u00fclt\u00fcr\u00fc"
    ],
    "name:ukr_x_preferred":[
        "\u0410\u043d\u0430\u0443"
    ],
    "name:unk_x_variant":[
        "Anau"
    ],
    "name:urd_x_preferred":[
        "\u0622\u0646\u0627\u0624"
    ],
    "name:uzb_x_preferred":[
        "Annau"
    ],
    "name:zho_x_preferred":[
        "\u5b89\u7d0d\u70cf"
    ],
    "qs_pg:aaroncc":"TM",
    "qs_pg:gn_country":"TM",
    "qs_pg:gn_fcode":"PPL",
    "qs_pg:gn_pop":27526,
    "qs_pg:name":"Annau",
    "qs_pg:photos_9r":0,
    "qs_pg:photos_sr":0,
    "qs_pg:pop_sr":7,
    "qs_pg:qs_pg_placetype":"locality",
    "wof:name":"Annau",
    "wof:placetype":"locality",
    "wof:population":27526
},
  "geometry": {"coordinates":[58.516,37.88757],"type":"Point"}
}