{
  "type": "Feature",
  "properties": {
    "gn:admin1_code":"02",
    "gn:asciiname":"Udzhi",
    "gn:country_code":"TM",
    "gn:dem":779,
    "gn:feature_class":"P",
    "gn:feature_code":"PPL",
    "gn:name":"Udzhi",
    "gn:population":0,
    "gn:timezone":"Asia/Ashgabat",
    "iso:country":"TM",
    "name:rus_x_preferred":[
        "\u0423\u0434\u0436\u0438"
    ],
    "wof:name":"Udzhi",
    "wof:placetype":"locality"
},
  "geometry": {"coordinates":[56.7298,38.36435],"type":"Point"}
}