{
  "type": "Feature",
  "properties": {
    "gn:admin1_code":"02",
    "gn:asciiname":"Garadepe",
    "gn:cc2":"TM",
    "gn:country_code":"TM",
    "gn:dem":-8,
    "gn:feature_class":"P",
    "gn:feature_code":"PPL",
    "gn:name":"Garadepe",
    "gn:population":0,
    "gn:timezone":"Asia/Ashgabat",
    "iso:country":"TM",
    "name:rus_x_preferred":[
        "\u041a\u0430\u0440\u0430\u0434\u0435\u043f\u0435"
    ],
    "name:und_x_variant":[
        "Karadepe",
        "Garadepe"
    ],
    "wof:name":"Garadepe",
    "wof:placetype":"locality"
},
  "geometry": {"coordinates":[54.03556,38.03222],"type":"Point"}
}