{
  "type": "Feature",
  "properties": {
    "gn:admin1_code":"00",
    "gn:asciiname":"Eski",
    "gn:country_code":"TM",
    "gn:dem":198,
    "gn:feature_class":"P",
    "gn:feature_code":"PPL",
    "gn:name":"Eski",
    "gn:population":0,
    "gn:timezone":"Asia/Ashgabat",
    "iso:country":"TM",
    "wof:name":"Eski",
    "wof:placetype":"locality"
},
  "geometry": {"coordinates":[63.86666999999999,38.81667],"type":"Point"}
}