{
  "type": "Feature",
  "properties": {
    "gn:admin1_code":"00",
    "gn:asciiname":"Imeni Kirova",
    "gn:country_code":"TM",
    "gn:dem":208,
    "gn:feature_class":"P",
    "gn:feature_code":"PPL",
    "gn:name":"Imeni Kirova",
    "gn:population":0,
    "gn:timezone":"Asia/Ashgabat",
    "iso:country":"TM",
    "name:und_x_variant":[
        "Berut",
        "Imeni Kirova"
    ],
    "wof:name":"Imeni Kirova",
    "wof:placetype":"locality"
},
  "geometry": {"coordinates":[64.03763000000001,38.5837],"type":"Point"}
}