{
  "type": "Feature",
  "properties": {
    "gn:admin1_code":"00",
    "gn:asciiname":"Irkli",
    "gn:country_code":"TM",
    "gn:dem":186,
    "gn:feature_class":"P",
    "gn:feature_code":"PPL",
    "gn:name":"Irkli",
    "gn:population":0,
    "gn:timezone":"Asia/Ashgabat",
    "iso:country":"TM",
    "wof:name":"Irkli",
    "wof:placetype":"locality"
},
  "geometry": {"coordinates":[54.30164,40.16809],"type":"Point"}
}