{
  "type": "Feature",
  "properties": {
    "gn:admin1_code":"00",
    "gn:asciiname":"Dzhuma-Bazar",
    "gn:country_code":"TM",
    "gn:dem":219,
    "gn:feature_class":"P",
    "gn:feature_code":"PPL",
    "gn:name":"Dzhuma-Bazar",
    "gn:population":0,
    "gn:timezone":"Asia/Ashgabat",
    "iso:country":"TM",
    "wof:name":"Dzhuma-Bazar",
    "wof:placetype":"locality"
},
  "geometry": {"coordinates":[64.46666999999999,38.23333],"type":"Point"}
}