{
  "type": "Feature",
  "properties": {
    "gn:admin1_code":"02",
    "gn:asciiname":"Goc",
    "gn:country_code":"TM",
    "gn:dem":76,
    "gn:feature_class":"P",
    "gn:feature_code":"PPL",
    "gn:name":"Go\u00e7",
    "gn:population":0,
    "gn:timezone":"Asia/Ashgabat",
    "iso:country":"TM",
    "name:rus_x_preferred":[
        "\u0421\u043e\u0432\u0445\u043e\u0437 \u0418\u043c\u0435\u043d\u0438 \u0424\u0440\u043e\u043b\u043e\u0432\u0430"
    ],
    "name:tuk_x_preferred":[
        "Go\u00e7"
    ],
    "name:und_x_variant":[
        "Kodsh",
        "Kodzh",
        "Koch",
        "Kodzha",
        "Sovkhoz Imeni Frolova"
    ],
    "wof:name":"Goc",
    "wof:placetype":"locality"
},
  "geometry": {"coordinates":[56.59591,38.81636],"type":"Point"}
}