{
  "type": "Feature",
  "properties": {
    "gn:admin1_code":"00",
    "gn:asciiname":"Turkmenistan",
    "gn:country_code":"TM",
    "gn:dem":143,
    "gn:feature_class":"P",
    "gn:feature_code":"PPL",
    "gn:name":"Turkmenistan",
    "gn:population":0,
    "gn:timezone":"Asia/Ashgabat",
    "iso:country":"TM",
    "wof:name":"Turkmenistan",
    "wof:placetype":"locality"
},
  "geometry": {"coordinates":[62.21379,40.46971],"type":"Point"}
}