{
  "type": "Feature",
  "properties": {
    "gn:admin1_code":"00",
    "gn:asciiname":"Siyadak-Sakar",
    "gn:country_code":"TM",
    "gn:dem":197,
    "gn:feature_class":"P",
    "gn:feature_code":"PPL",
    "gn:name":"Siyadak-Sakar",
    "gn:population":0,
    "gn:timezone":"Asia/Ashgabat",
    "iso:country":"TM",
    "name:und_x_variant":[
        "Siyardyk Sakar",
        "Khodzholok-Aragly",
        "Khodzholok",
        "Siyadyk-Sakar",
        "Siyadak-Sakar"
    ],
    "wof:name":"Siyadak-Sakar",
    "wof:placetype":"locality"
},
  "geometry": {"coordinates":[63.79324,38.92231],"type":"Point"}
}