{
  "type": "Feature",
  "properties": {
    "gn:admin1_code":"00",
    "gn:asciiname":"Sary-Bash",
    "gn:country_code":"TM",
    "gn:dem":223,
    "gn:feature_class":"P",
    "gn:feature_code":"PPL",
    "gn:name":"Sary-Bash",
    "gn:population":0,
    "gn:timezone":"Asia/Ashgabat",
    "iso:country":"TM",
    "wof:name":"Sary-Bash",
    "wof:placetype":"locality"
},
  "geometry": {"coordinates":[64.61667,38.21667],"type":"Point"}
}