{
  "type": "Feature",
  "properties": {
    "gn:admin1_code":"01",
    "gn:asciiname":"Kel'",
    "gn:country_code":"TM",
    "gn:dem":127,
    "gn:feature_class":"P",
    "gn:feature_code":"PPL",
    "gn:name":"Kel\u2019",
    "gn:population":0,
    "gn:timezone":"Asia/Ashgabat",
    "iso:country":"TM",
    "name:rus_x_preferred":[
        "Kel\u2019"
    ],
    "name:rus_x_variant":[
        "\u041a\u0435\u043b\u044c"
    ],
    "wof:name":"Kel'",
    "wof:placetype":"locality"
},
  "geometry": {"coordinates":[57.40691,38.48507],"type":"Point"}
}