{
  "type": "Feature",
  "properties": {
    "gn:admin1_code":"00",
    "gn:asciiname":"Chatryak",
    "gn:cc2":"TM",
    "gn:country_code":"TM",
    "gn:dem":229,
    "gn:feature_class":"P",
    "gn:feature_code":"PPL",
    "gn:name":"Chatryak",
    "gn:population":0,
    "gn:timezone":"Asia/Ashgabat",
    "iso:country":"TM",
    "name:und_x_variant":[
        "Chatryat",
        "Chatrak",
        "Chatryak"
    ],
    "wof:name":"Chatryak",
    "wof:placetype":"locality"
},
  "geometry": {"coordinates":[64.73333000000001,38.21667],"type":"Point"}
}