{
  "type": "Feature",
  "properties": {
    "gn:admin1_code":"00",
    "gn:asciiname":"Chekmen",
    "gn:country_code":"TM",
    "gn:dem":250,
    "gn:feature_class":"P",
    "gn:feature_code":"PPL",
    "gn:name":"Chekmen",
    "gn:population":0,
    "gn:timezone":"Asia/Ashgabat",
    "iso:country":"TM",
    "wof:name":"Chekmen",
    "wof:placetype":"locality"
},
  "geometry": {"coordinates":[65.25,37.65],"type":"Point"}
}