{
  "type": "Feature",
  "properties": {
    "gn:admin1_code":"01",
    "gn:asciiname":"Talkhanly",
    "gn:country_code":"TM",
    "gn:dem":190,
    "gn:feature_class":"P",
    "gn:feature_code":"PPL",
    "gn:name":"Talkhanly",
    "gn:population":0,
    "gn:timezone":"Asia/Ashgabat",
    "iso:country":"TM",
    "name:rus_x_preferred":[
        "\u0422\u0430\u043b\u0445\u0430\u043d\u043b\u044b"
    ],
    "wof:name":"Talkhanly",
    "wof:placetype":"locality"
},
  "geometry": {"coordinates":[58.20235,38.1082],"type":"Point"}
}