{
  "type": "Feature",
  "properties": {
    "gn:admin1_code":"00",
    "gn:asciiname":"Adzhikui",
    "gn:cc2":"TM",
    "gn:country_code":"TM",
    "gn:dem":57,
    "gn:feature_class":"P",
    "gn:feature_code":"PPL",
    "gn:name":"Adzhikui",
    "gn:population":0,
    "gn:timezone":"Asia/Ashgabat",
    "iso:country":"TM",
    "name:und_x_variant":[
        "Adzhi-Kuyu",
        "Adzhikui"
    ],
    "wof:name":"Adzhikui",
    "wof:placetype":"locality"
},
  "geometry": {"coordinates":[54.98333,39.76667],"type":"Point"}
}