{
  "type": "Feature",
  "properties": {
    "gn:admin1_code":"01",
    "gn:asciiname":"Alam",
    "gn:country_code":"TM",
    "gn:dem":254,
    "gn:feature_class":"P",
    "gn:feature_code":"PPL",
    "gn:name":"Alam",
    "gn:population":0,
    "gn:timezone":"Asia/Ashgabat",
    "iso:country":"TM",
    "name:und_x_variant":[
        "Karaman Vtoroy",
        "Alam"
    ],
    "wof:name":"Alam",
    "wof:placetype":"locality"
},
  "geometry": {"coordinates":[61.12879,36.75937],"type":"Point"}
}