{
  "type": "Feature",
  "properties": {
    "gn:admin1_code":"00",
    "gn:asciiname":"Aydin",
    "gn:country_code":"TM",
    "gn:dem":-12,
    "gn:feature_class":"P",
    "gn:feature_code":"PPL",
    "gn:name":"Aydin",
    "gn:population":0,
    "gn:timezone":"Asia/Ashgabat",
    "iso:country":"TM",
    "wof:name":"Aydin",
    "wof:placetype":"locality"
},
  "geometry": {"coordinates":[54.81667,39.35],"type":"Point"}
}