{
  "type": "Feature",
  "properties": {
    "gn:admin1_code":"05",
    "gn:asciiname":"Imeni Chapayeva",
    "gn:country_code":"TM",
    "gn:dem":291,
    "gn:feature_class":"P",
    "gn:feature_code":"PPL",
    "gn:name":"Imeni Chapayeva",
    "gn:population":0,
    "gn:timezone":"Asia/Ashgabat",
    "iso:country":"TM",
    "wof:name":"Imeni Chapayeva",
    "wof:placetype":"locality"
},
  "geometry": {"coordinates":[62.45886,36.71678],"type":"Point"}
}