{
  "type": "Feature",
  "properties": {
    "gn:admin1_code":"02",
    "gn:asciiname":"Kayrayuz",
    "gn:cc2":"TM",
    "gn:country_code":"TM",
    "gn:dem":-22,
    "gn:feature_class":"P",
    "gn:feature_code":"PPL",
    "gn:name":"Kayrayuz",
    "gn:population":0,
    "gn:timezone":"Asia/Ashgabat",
    "iso:country":"TM",
    "name:und_x_variant":[
        "Gayrayuz",
        "Kayrayuz"
    ],
    "wof:name":"Kayrayuz",
    "wof:placetype":"locality"
},
  "geometry": {"coordinates":[53.18639,39.53778],"type":"Point"}
}