{
  "type": "Feature",
  "properties": {
    "gn:admin1_code":"00",
    "gn:asciiname":"Khodzhakala",
    "gn:country_code":"TM",
    "gn:dem":187,
    "gn:feature_class":"P",
    "gn:feature_code":"PPL",
    "gn:name":"Khodzhakala",
    "gn:population":0,
    "gn:timezone":"Asia/Ashgabat",
    "iso:country":"TM",
    "name:fas_x_preferred":[
        "\u062e\u0648\u0627\u062c\u0647\u200c\u0642\u0644\u0639\u0647"
    ],
    "wof:name":"Khodzhakala",
    "wof:placetype":"locality"
},
  "geometry": {"coordinates":[63.43333000000001,39.13333],"type":"Point"}
}