{
  "type": "Feature",
  "properties": {
    "gn:admin1_code":"00",
    "gn:asciiname":"Chakal",
    "gn:cc2":"TM",
    "gn:country_code":"TM",
    "gn:dem":167,
    "gn:feature_class":"P",
    "gn:feature_code":"PPL",
    "gn:name":"Chakal",
    "gn:population":0,
    "gn:timezone":"Asia/Ashgabat",
    "iso:country":"TM",
    "name:ces_x_preferred":[
        "Chakal"
    ],
    "name:dan_x_preferred":[
        "Chakal"
    ],
    "name:deu_x_preferred":[
        "Chakal"
    ],
    "name:pol_x_preferred":[
        "Chakal"
    ],
    "name:por_x_preferred":[
        "Chakal"
    ],
    "name:und_x_variant":[
        "Chanal",
        "Chakal"
    ],
    "wof:name":"Chakal",
    "wof:placetype":"locality"
},
  "geometry": {"coordinates":[62.93333000000001,39.35],"type":"Point"}
}