{
  "type": "Feature",
  "properties": {
    "gn:admin1_code":"00",
    "gn:asciiname":"Yazdepe",
    "gn:cc2":"TM",
    "gn:country_code":"TM",
    "gn:dem":190,
    "gn:feature_class":"P",
    "gn:feature_code":"PPL",
    "gn:name":"Yazdepe",
    "gn:population":0,
    "gn:timezone":"Asia/Ashgabat",
    "iso:country":"TM",
    "name:und_x_variant":[
        "Yaz-Tepe",
        "Yazdepe"
    ],
    "wof:name":"Yazdepe",
    "wof:placetype":"locality"
},
  "geometry": {"coordinates":[63.38333000000001,39.08333],"type":"Point"}
}