{
  "type": "Feature",
  "properties": {
    "gn:admin1_code":"00",
    "gn:asciiname":"Kyrkkui",
    "gn:country_code":"TM",
    "gn:dem":120,
    "gn:feature_class":"P",
    "gn:feature_code":"PPL",
    "gn:name":"Kyrkkui",
    "gn:population":0,
    "gn:timezone":"Asia/Ashgabat",
    "iso:country":"TM",
    "name:und_x_variant":[
        "Kyrk-Kuyu",
        "Kyrkkui"
    ],
    "wof:name":"Kyrkkui",
    "wof:placetype":"locality"
},
  "geometry": {"coordinates":[59.42929,38.19492],"type":"Point"}
}