{
  "type": "Feature",
  "properties": {
    "gn:admin1_code":"00",
    "gn:asciiname":"Imeni Poltoratskogo",
    "gn:country_code":"TM",
    "gn:dem":224,
    "gn:feature_class":"P",
    "gn:feature_code":"PPL",
    "gn:name":"Imeni Poltoratskogo",
    "gn:population":0,
    "gn:timezone":"Asia/Ashgabat",
    "iso:country":"TM",
    "wof:name":"Imeni Poltoratskogo",
    "wof:placetype":"locality"
},
  "geometry": {"coordinates":[61.93241999999999,37.60601],"type":"Point"}
}