{
  "type": "Feature",
  "properties": {
    "gn:admin1_code":"00",
    "gn:asciiname":"Chagyl",
    "gn:country_code":"TM",
    "gn:dem":113,
    "gn:feature_class":"P",
    "gn:feature_code":"PPL",
    "gn:name":"Chagyl",
    "gn:population":0,
    "gn:timezone":"Asia/Ashgabat",
    "iso:country":"TM",
    "wof:name":"Chagyl",
    "wof:placetype":"locality"
},
  "geometry": {"coordinates":[55.3786,40.78417],"type":"Point"}
}