{
  "type": "Feature",
  "properties": {
    "gn:admin1_code":"00",
    "gn:asciiname":"Kyzylkoshun",
    "gn:cc2":"TM",
    "gn:country_code":"TM",
    "gn:dem":228,
    "gn:feature_class":"P",
    "gn:feature_code":"PPL",
    "gn:name":"Kyzylkoshun",
    "gn:population":0,
    "gn:timezone":"Asia/Ashgabat",
    "iso:country":"TM",
    "name:und_x_variant":[
        "Dushame-Chakyr",
        "Chakyr",
        "Kyzylkoshun"
    ],
    "wof:name":"Kyzylkoshun",
    "wof:placetype":"locality"
},
  "geometry": {"coordinates":[64.66667,38.13333],"type":"Point"}
}