{
  "type": "Feature",
  "properties": {
    "gn:admin1_code":"00",
    "gn:asciiname":"Imeni Lenina",
    "gn:country_code":"TM",
    "gn:dem":184,
    "gn:feature_class":"P",
    "gn:feature_code":"PPL",
    "gn:name":"Imeni Lenina",
    "gn:population":0,
    "gn:timezone":"Asia/Ashgabat",
    "iso:country":"TM",
    "wof:name":"Imeni Lenina",
    "wof:placetype":"locality"
},
  "geometry": {"coordinates":[63.23757,39.18668],"type":"Point"}
}